<?xml version='1.0' encoding='UTF-8'?>
<data>
<FIN_PAYMENT_SCHEDULE>
  <FIN_PAYMENT_SCHEDULE_ID><![CDATA[008C9D3C3EDE416FB0D7CD0E25422189]]></FIN_PAYMENT_SCHEDULE_ID>
  <AD_CLIENT_ID><![CDATA[39363B0921BB4293B48383844325E84C]]></AD_CLIENT_ID>
  <AD_ORG_ID><![CDATA[D270A5AC50874F8BA67A88EE977F8E3B]]></AD_ORG_ID>
  <CREATED><![CDATA[2014-04-22 15:47:17.361]]></CREATED>
  <CREATEDBY><![CDATA[3073EDF96A3C42CC86C7069E379522D2]]></CREATEDBY>
  <UPDATED><![CDATA[2014-04-22 15:47:17.484]]></UPDATED>
  <UPDATEDBY><![CDATA[3073EDF96A3C42CC86C7069E379522D2]]></UPDATEDBY>
  <C_ORDER_ID><![CDATA[2C293D97438718534F47C1AF02693ECA]]></C_ORDER_ID>
  <DUEDATE><![CDATA[2014-04-22 00:00:00.0]]></DUEDATE>
  <FIN_PAYMENTMETHOD_ID><![CDATA[45A202BF44884F05B8A1BF741E2063B6]]></FIN_PAYMENTMETHOD_ID>
  <C_CURRENCY_ID><![CDATA[102]]></C_CURRENCY_ID>
  <AMOUNT><![CDATA[109.00]]></AMOUNT>
  <PAIDAMT><![CDATA[109.00]]></PAIDAMT>
  <OUTSTANDINGAMT><![CDATA[0.00]]></OUTSTANDINGAMT>
  <ISACTIVE><![CDATA[Y]]></ISACTIVE>
  <UPDATE_PAYMENT_PLAN><![CDATA[Y]]></UPDATE_PAYMENT_PLAN>
  <EXPECTEDDATE><![CDATA[2014-04-22 00:00:00.0]]></EXPECTEDDATE>
  <EM_APRM_MODIF_PAYM_SCHED><![CDATA[N]]></EM_APRM_MODIF_PAYM_SCHED>
  <EM_APRM_MODIF_PAYM_OUT_SCHED><![CDATA[N]]></EM_APRM_MODIF_PAYM_OUT_SCHED>
</FIN_PAYMENT_SCHEDULE>

<FIN_PAYMENT_SCHEDULE>
  <FIN_PAYMENT_SCHEDULE_ID><![CDATA[036DA8CEA84B4D1FBA1E518A0F57BD86]]></FIN_PAYMENT_SCHEDULE_ID>
  <AD_CLIENT_ID><![CDATA[39363B0921BB4293B48383844325E84C]]></AD_CLIENT_ID>
  <AD_ORG_ID><![CDATA[D270A5AC50874F8BA67A88EE977F8E3B]]></AD_ORG_ID>
  <CREATED><![CDATA[2013-07-04 23:01:16.702]]></CREATED>
  <CREATEDBY><![CDATA[0]]></CREATEDBY>
  <UPDATED><![CDATA[2013-07-04 23:01:16.702]]></UPDATED>
  <UPDATEDBY><![CDATA[0]]></UPDATEDBY>
  <C_INVOICE_ID><![CDATA[94DE25834E0C4B0583958BCCDAC605FA]]></C_INVOICE_ID>
  <DUEDATE><![CDATA[2012-07-24 00:00:00.0]]></DUEDATE>
  <FIN_PAYMENTMETHOD_ID><![CDATA[45A202BF44884F05B8A1BF741E2063B6]]></FIN_PAYMENTMETHOD_ID>
  <C_CURRENCY_ID><![CDATA[102]]></C_CURRENCY_ID>
  <AMOUNT><![CDATA[63.4]]></AMOUNT>
  <PAIDAMT><![CDATA[63.4]]></PAIDAMT>
  <OUTSTANDINGAMT><![CDATA[0.0]]></OUTSTANDINGAMT>
  <ISACTIVE><![CDATA[Y]]></ISACTIVE>
  <UPDATE_PAYMENT_PLAN><![CDATA[Y]]></UPDATE_PAYMENT_PLAN>
  <EXPECTEDDATE><![CDATA[2012-07-24 00:00:00.0]]></EXPECTEDDATE>
  <EM_APRM_MODIF_PAYM_SCHED><![CDATA[N]]></EM_APRM_MODIF_PAYM_SCHED>
  <EM_APRM_MODIF_PAYM_OUT_SCHED><![CDATA[N]]></EM_APRM_MODIF_PAYM_OUT_SCHED>
</FIN_PAYMENT_SCHEDULE>

<FIN_PAYMENT_SCHEDULE>
  <FIN_PAYMENT_SCHEDULE_ID><![CDATA[0571924ECEC54AE692BBC70BD59FFBBE]]></FIN_PAYMENT_SCHEDULE_ID>
  <AD_CLIENT_ID><![CDATA[39363B0921BB4293B48383844325E84C]]></AD_CLIENT_ID>
  <AD_ORG_ID><![CDATA[B5DE96143D6642228E3B9DEC69886A47]]></AD_ORG_ID>
  <CREATED><![CDATA[2013-07-04 23:01:16.701]]></CREATED>
  <CREATEDBY><![CDATA[0]]></CREATEDBY>
  <UPDATED><![CDATA[2013-07-04 23:01:16.701]]></UPDATED>
  <UPDATEDBY><![CDATA[0]]></UPDATEDBY>
  <C_ORDER_ID><![CDATA[ED384F0179CC440E886ED321CF973D56]]></C_ORDER_ID>
  <DUEDATE><![CDATA[2012-07-24 00:00:00.0]]></DUEDATE>
  <FIN_PAYMENTMETHOD_ID><![CDATA[45A202BF44884F05B8A1BF741E2063B6]]></FIN_PAYMENTMETHOD_ID>
  <C_CURRENCY_ID><![CDATA[102]]></C_CURRENCY_ID>
  <AMOUNT><![CDATA[198.0]]></AMOUNT>
  <PAIDAMT><![CDATA[198.0]]></PAIDAMT>
  <OUTSTANDINGAMT><![CDATA[0.0]]></OUTSTANDINGAMT>
  <ISACTIVE><![CDATA[Y]]></ISACTIVE>
  <UPDATE_PAYMENT_PLAN><![CDATA[Y]]></UPDATE_PAYMENT_PLAN>
  <EXPECTEDDATE><![CDATA[2012-07-24 00:00:00.0]]></EXPECTEDDATE>
  <EM_APRM_MODIF_PAYM_SCHED><![CDATA[N]]></EM_APRM_MODIF_PAYM_SCHED>
  <EM_APRM_MODIF_PAYM_OUT_SCHED><![CDATA[N]]></EM_APRM_MODIF_PAYM_OUT_SCHED>
</FIN_PAYMENT_SCHEDULE>

<FIN_PAYMENT_SCHEDULE>
  <FIN_PAYMENT_SCHEDULE_ID><![CDATA[0DD3AA018868471597D264EDCD6BD962]]></FIN_PAYMENT_SCHEDULE_ID>
  <AD_CLIENT_ID><![CDATA[39363B0921BB4293B48383844325E84C]]></AD_CLIENT_ID>
  <AD_ORG_ID><![CDATA[3B187EC130A549A7A9388F8060EF156D]]></AD_ORG_ID>
  <CREATED><![CDATA[2013-07-04 23:01:16.702]]></CREATED>
  <CREATEDBY><![CDATA[0]]></CREATEDBY>
  <UPDATED><![CDATA[2013-07-04 23:01:16.702]]></UPDATED>
  <UPDATEDBY><![CDATA[0]]></UPDATEDBY>
  <C_INVOICE_ID><![CDATA[4944520D911249F195DC01D6D0C88C96]]></C_INVOICE_ID>
  <DUEDATE><![CDATA[2012-07-24 12:45:20.666]]></DUEDATE>
  <FIN_PAYMENTMETHOD_ID><![CDATA[45A202BF44884F05B8A1BF741E2063B6]]></FIN_PAYMENTMETHOD_ID>
  <C_CURRENCY_ID><![CDATA[102]]></C_CURRENCY_ID>
  <AMOUNT><![CDATA[314.9]]></AMOUNT>
  <PAIDAMT><![CDATA[314.9]]></PAIDAMT>
  <OUTSTANDINGAMT><![CDATA[0]]></OUTSTANDINGAMT>
  <ISACTIVE><![CDATA[Y]]></ISACTIVE>
  <UPDATE_PAYMENT_PLAN><![CDATA[Y]]></UPDATE_PAYMENT_PLAN>
  <EXPECTEDDATE><![CDATA[2012-07-24 12:45:20.666]]></EXPECTEDDATE>
  <EM_APRM_MODIF_PAYM_SCHED><![CDATA[N]]></EM_APRM_MODIF_PAYM_SCHED>
  <EM_APRM_MODIF_PAYM_OUT_SCHED><![CDATA[N]]></EM_APRM_MODIF_PAYM_OUT_SCHED>
</FIN_PAYMENT_SCHEDULE>

<FIN_PAYMENT_SCHEDULE>
  <FIN_PAYMENT_SCHEDULE_ID><![CDATA[1382EDE2172446BABD7AB744558FA144]]></FIN_PAYMENT_SCHEDULE_ID>
  <AD_CLIENT_ID><![CDATA[39363B0921BB4293B48383844325E84C]]></AD_CLIENT_ID>
  <AD_ORG_ID><![CDATA[D270A5AC50874F8BA67A88EE977F8E3B]]></AD_ORG_ID>
  <CREATED><![CDATA[2013-07-04 23:01:16.745]]></CREATED>
  <CREATEDBY><![CDATA[0]]></CREATEDBY>
  <UPDATED><![CDATA[2013-07-04 23:01:16.745]]></UPDATED>
  <UPDATEDBY><![CDATA[0]]></UPDATEDBY>
  <C_ORDER_ID><![CDATA[94048AC51C9F0618C98CF6D6DC60CF10]]></C_ORDER_ID>
  <DUEDATE><![CDATA[2013-03-01 00:00:00.0]]></DUEDATE>
  <FIN_PAYMENTMETHOD_ID><![CDATA[45A202BF44884F05B8A1BF741E2063B6]]></FIN_PAYMENTMETHOD_ID>
  <C_CURRENCY_ID><![CDATA[102]]></C_CURRENCY_ID>
  <AMOUNT><![CDATA[399.00]]></AMOUNT>
  <PAIDAMT><![CDATA[70.00]]></PAIDAMT>
  <OUTSTANDINGAMT><![CDATA[329.00]]></OUTSTANDINGAMT>
  <ISACTIVE><![CDATA[Y]]></ISACTIVE>
  <UPDATE_PAYMENT_PLAN><![CDATA[Y]]></UPDATE_PAYMENT_PLAN>
  <EXPECTEDDATE><![CDATA[2013-03-01 00:00:00.0]]></EXPECTEDDATE>
  <EM_APRM_MODIF_PAYM_SCHED><![CDATA[N]]></EM_APRM_MODIF_PAYM_SCHED>
  <EM_APRM_MODIF_PAYM_OUT_SCHED><![CDATA[N]]></EM_APRM_MODIF_PAYM_OUT_SCHED>
</FIN_PAYMENT_SCHEDULE>

<FIN_PAYMENT_SCHEDULE>
  <FIN_PAYMENT_SCHEDULE_ID><![CDATA[188132DBDDAB4084BF8E974FC72C48D6]]></FIN_PAYMENT_SCHEDULE_ID>
  <AD_CLIENT_ID><![CDATA[39363B0921BB4293B48383844325E84C]]></AD_CLIENT_ID>
  <AD_ORG_ID><![CDATA[D270A5AC50874F8BA67A88EE977F8E3B]]></AD_ORG_ID>
  <CREATED><![CDATA[2013-07-04 23:01:16.745]]></CREATED>
  <CREATEDBY><![CDATA[0]]></CREATEDBY>
  <UPDATED><![CDATA[2013-07-04 23:01:16.745]]></UPDATED>
  <UPDATEDBY><![CDATA[0]]></UPDATEDBY>
  <C_ORDER_ID><![CDATA[4D239E84E85084FF735666FF8DEF65E6]]></C_ORDER_ID>
  <DUEDATE><![CDATA[2013-03-01 00:00:00.0]]></DUEDATE>
  <FIN_PAYMENTMETHOD_ID><![CDATA[45A202BF44884F05B8A1BF741E2063B6]]></FIN_PAYMENTMETHOD_ID>
  <C_CURRENCY_ID><![CDATA[102]]></C_CURRENCY_ID>
  <AMOUNT><![CDATA[0]]></AMOUNT>
  <PAIDAMT><![CDATA[0]]></PAIDAMT>
  <OUTSTANDINGAMT><![CDATA[0]]></OUTSTANDINGAMT>
  <ISACTIVE><![CDATA[Y]]></ISACTIVE>
  <UPDATE_PAYMENT_PLAN><![CDATA[Y]]></UPDATE_PAYMENT_PLAN>
  <EXPECTEDDATE><![CDATA[2013-03-01 00:00:00.0]]></EXPECTEDDATE>
  <EM_APRM_MODIF_PAYM_SCHED><![CDATA[N]]></EM_APRM_MODIF_PAYM_SCHED>
  <EM_APRM_MODIF_PAYM_OUT_SCHED><![CDATA[N]]></EM_APRM_MODIF_PAYM_OUT_SCHED>
</FIN_PAYMENT_SCHEDULE>

<FIN_PAYMENT_SCHEDULE>
  <FIN_PAYMENT_SCHEDULE_ID><![CDATA[1A07F1984E974E09B6D52BBEF100BBBF]]></FIN_PAYMENT_SCHEDULE_ID>
  <AD_CLIENT_ID><![CDATA[39363B0921BB4293B48383844325E84C]]></AD_CLIENT_ID>
  <AD_ORG_ID><![CDATA[BF129721D9FB4EB0819509934153E972]]></AD_ORG_ID>
  <CREATED><![CDATA[2013-07-04 23:01:16.745]]></CREATED>
  <CREATEDBY><![CDATA[0]]></CREATEDBY>
  <UPDATED><![CDATA[2013-07-04 23:01:16.745]]></UPDATED>
  <UPDATEDBY><![CDATA[0]]></UPDATEDBY>
  <C_INVOICE_ID><![CDATA[59FADEAAFF2745D387674CC9D4AD5F16]]></C_INVOICE_ID>
  <DUEDATE><![CDATA[2012-10-22 00:00:00.0]]></DUEDATE>
  <FIN_PAYMENTMETHOD_ID><![CDATA[5A741F883A31408CA3AC097D76AA6D32]]></FIN_PAYMENTMETHOD_ID>
  <C_CURRENCY_ID><![CDATA[102]]></C_CURRENCY_ID>
  <AMOUNT><![CDATA[1389370.40]]></AMOUNT>
  <PAIDAMT><![CDATA[0]]></PAIDAMT>
  <OUTSTANDINGAMT><![CDATA[1389370.40]]></OUTSTANDINGAMT>
  <ISACTIVE><![CDATA[Y]]></ISACTIVE>
  <UPDATE_PAYMENT_PLAN><![CDATA[Y]]></UPDATE_PAYMENT_PLAN>
  <EXPECTEDDATE><![CDATA[2012-10-22 00:00:00.0]]></EXPECTEDDATE>
  <EM_APRM_MODIF_PAYM_SCHED><![CDATA[N]]></EM_APRM_MODIF_PAYM_SCHED>
  <EM_APRM_MODIF_PAYM_OUT_SCHED><![CDATA[N]]></EM_APRM_MODIF_PAYM_OUT_SCHED>
</FIN_PAYMENT_SCHEDULE>

<FIN_PAYMENT_SCHEDULE>
  <FIN_PAYMENT_SCHEDULE_ID><![CDATA[1C4DD23C513247BFA2D250836C4E87C7]]></FIN_PAYMENT_SCHEDULE_ID>
  <AD_CLIENT_ID><![CDATA[39363B0921BB4293B48383844325E84C]]></AD_CLIENT_ID>
  <AD_ORG_ID><![CDATA[B5DE96143D6642228E3B9DEC69886A47]]></AD_ORG_ID>
  <CREATED><![CDATA[2014-04-19 20:37:03.0]]></CREATED>
  <CREATEDBY><![CDATA[100]]></CREATEDBY>
  <UPDATED><![CDATA[2014-04-19 20:37:03.0]]></UPDATED>
  <UPDATEDBY><![CDATA[100]]></UPDATEDBY>
  <C_ORDER_ID><![CDATA[355DDD8BC79D4A55BD501AA3C4886704]]></C_ORDER_ID>
  <DUEDATE><![CDATA[2014-04-19 00:00:00.0]]></DUEDATE>
  <FIN_PAYMENTMETHOD_ID><![CDATA[5A741F883A31408CA3AC097D76AA6D32]]></FIN_PAYMENTMETHOD_ID>
  <C_CURRENCY_ID><![CDATA[102]]></C_CURRENCY_ID>
  <AMOUNT><![CDATA[76725.00]]></AMOUNT>
  <PAIDAMT><![CDATA[0]]></PAIDAMT>
  <OUTSTANDINGAMT><![CDATA[76725.00]]></OUTSTANDINGAMT>
  <ISACTIVE><![CDATA[Y]]></ISACTIVE>
  <UPDATE_PAYMENT_PLAN><![CDATA[Y]]></UPDATE_PAYMENT_PLAN>
  <EXPECTEDDATE><![CDATA[2014-04-19 00:00:00.0]]></EXPECTEDDATE>
  <EM_APRM_MODIF_PAYM_SCHED><![CDATA[N]]></EM_APRM_MODIF_PAYM_SCHED>
  <EM_APRM_MODIF_PAYM_OUT_SCHED><![CDATA[N]]></EM_APRM_MODIF_PAYM_OUT_SCHED>
</FIN_PAYMENT_SCHEDULE>

<FIN_PAYMENT_SCHEDULE>
  <FIN_PAYMENT_SCHEDULE_ID><![CDATA[1C8FB856EB34487AB1057AFD774BCEC7]]></FIN_PAYMENT_SCHEDULE_ID>
  <AD_CLIENT_ID><![CDATA[39363B0921BB4293B48383844325E84C]]></AD_CLIENT_ID>
  <AD_ORG_ID><![CDATA[D270A5AC50874F8BA67A88EE977F8E3B]]></AD_ORG_ID>
  <CREATED><![CDATA[2013-07-04 23:01:16.703]]></CREATED>
  <CREATEDBY><![CDATA[0]]></CREATEDBY>
  <UPDATED><![CDATA[2013-07-04 23:01:16.703]]></UPDATED>
  <UPDATEDBY><![CDATA[0]]></UPDATEDBY>
  <C_ORDER_ID><![CDATA[EBE12475E25C439F8BE0BE8CE8296DB8]]></C_ORDER_ID>
  <DUEDATE><![CDATA[2012-07-24 00:00:00.0]]></DUEDATE>
  <FIN_PAYMENTMETHOD_ID><![CDATA[45A202BF44884F05B8A1BF741E2063B6]]></FIN_PAYMENTMETHOD_ID>
  <C_CURRENCY_ID><![CDATA[102]]></C_CURRENCY_ID>
  <AMOUNT><![CDATA[110.5]]></AMOUNT>
  <PAIDAMT><![CDATA[110.5]]></PAIDAMT>
  <OUTSTANDINGAMT><![CDATA[0.0]]></OUTSTANDINGAMT>
  <ISACTIVE><![CDATA[Y]]></ISACTIVE>
  <UPDATE_PAYMENT_PLAN><![CDATA[Y]]></UPDATE_PAYMENT_PLAN>
  <EXPECTEDDATE><![CDATA[2012-07-24 00:00:00.0]]></EXPECTEDDATE>
  <EM_APRM_MODIF_PAYM_SCHED><![CDATA[N]]></EM_APRM_MODIF_PAYM_SCHED>
  <EM_APRM_MODIF_PAYM_OUT_SCHED><![CDATA[N]]></EM_APRM_MODIF_PAYM_OUT_SCHED>
</FIN_PAYMENT_SCHEDULE>

<FIN_PAYMENT_SCHEDULE>
  <FIN_PAYMENT_SCHEDULE_ID><![CDATA[203BA646BEC54303B15994E49EFC6859]]></FIN_PAYMENT_SCHEDULE_ID>
  <AD_CLIENT_ID><![CDATA[39363B0921BB4293B48383844325E84C]]></AD_CLIENT_ID>
  <AD_ORG_ID><![CDATA[3B187EC130A549A7A9388F8060EF156D]]></AD_ORG_ID>
  <CREATED><![CDATA[2015-11-26 11:49:54.0]]></CREATED>
  <CREATEDBY><![CDATA[100]]></CREATEDBY>
  <UPDATED><![CDATA[2015-11-26 11:49:54.0]]></UPDATED>
  <UPDATEDBY><![CDATA[100]]></UPDATEDBY>
  <C_ORDER_ID><![CDATA[2730D75C253C493F853520CE151DE848]]></C_ORDER_ID>
  <DUEDATE><![CDATA[2015-11-26 00:00:00.0]]></DUEDATE>
  <FIN_PAYMENTMETHOD_ID><![CDATA[5A741F883A31408CA3AC097D76AA6D32]]></FIN_PAYMENTMETHOD_ID>
  <C_CURRENCY_ID><![CDATA[102]]></C_CURRENCY_ID>
  <AMOUNT><![CDATA[20000.00]]></AMOUNT>
  <PAIDAMT><![CDATA[0]]></PAIDAMT>
  <OUTSTANDINGAMT><![CDATA[20000.00]]></OUTSTANDINGAMT>
  <ISACTIVE><![CDATA[Y]]></ISACTIVE>
  <UPDATE_PAYMENT_PLAN><![CDATA[Y]]></UPDATE_PAYMENT_PLAN>
  <EXPECTEDDATE><![CDATA[2015-11-26 00:00:00.0]]></EXPECTEDDATE>
  <EM_APRM_MODIF_PAYM_SCHED><![CDATA[N]]></EM_APRM_MODIF_PAYM_SCHED>
  <EM_APRM_MODIF_PAYM_OUT_SCHED><![CDATA[N]]></EM_APRM_MODIF_PAYM_OUT_SCHED>
</FIN_PAYMENT_SCHEDULE>

<FIN_PAYMENT_SCHEDULE>
  <FIN_PAYMENT_SCHEDULE_ID><![CDATA[2CF83FB3A4B14E5CAF6F0B6C863A3F60]]></FIN_PAYMENT_SCHEDULE_ID>
  <AD_CLIENT_ID><![CDATA[39363B0921BB4293B48383844325E84C]]></AD_CLIENT_ID>
  <AD_ORG_ID><![CDATA[D270A5AC50874F8BA67A88EE977F8E3B]]></AD_ORG_ID>
  <CREATED><![CDATA[2014-04-22 15:47:47.078]]></CREATED>
  <CREATEDBY><![CDATA[3073EDF96A3C42CC86C7069E379522D2]]></CREATEDBY>
  <UPDATED><![CDATA[2014-04-22 15:47:47.269]]></UPDATED>
  <UPDATEDBY><![CDATA[3073EDF96A3C42CC86C7069E379522D2]]></UPDATEDBY>
  <C_INVOICE_ID><![CDATA[FA6CC080ABC54F91AB252A37AAD4204D]]></C_INVOICE_ID>
  <DUEDATE><![CDATA[2014-04-22 15:47:45.0]]></DUEDATE>
  <FIN_PAYMENTMETHOD_ID><![CDATA[45A202BF44884F05B8A1BF741E2063B6]]></FIN_PAYMENTMETHOD_ID>
  <C_CURRENCY_ID><![CDATA[102]]></C_CURRENCY_ID>
  <AMOUNT><![CDATA[218.00]]></AMOUNT>
  <PAIDAMT><![CDATA[218.00]]></PAIDAMT>
  <OUTSTANDINGAMT><![CDATA[0]]></OUTSTANDINGAMT>
  <ISACTIVE><![CDATA[Y]]></ISACTIVE>
  <UPDATE_PAYMENT_PLAN><![CDATA[Y]]></UPDATE_PAYMENT_PLAN>
  <EXPECTEDDATE><![CDATA[2014-04-22 15:47:45.0]]></EXPECTEDDATE>
  <EM_APRM_MODIF_PAYM_SCHED><![CDATA[N]]></EM_APRM_MODIF_PAYM_SCHED>
  <EM_APRM_MODIF_PAYM_OUT_SCHED><![CDATA[N]]></EM_APRM_MODIF_PAYM_OUT_SCHED>
</FIN_PAYMENT_SCHEDULE>

<FIN_PAYMENT_SCHEDULE>
  <FIN_PAYMENT_SCHEDULE_ID><![CDATA[2E5E33497D714161B82C22282241869D]]></FIN_PAYMENT_SCHEDULE_ID>
  <AD_CLIENT_ID><![CDATA[39363B0921BB4293B48383844325E84C]]></AD_CLIENT_ID>
  <AD_ORG_ID><![CDATA[B5DE96143D6642228E3B9DEC69886A47]]></AD_ORG_ID>
  <CREATED><![CDATA[2013-07-04 23:01:16.704]]></CREATED>
  <CREATEDBY><![CDATA[0]]></CREATEDBY>
  <UPDATED><![CDATA[2013-07-04 23:01:16.704]]></UPDATED>
  <UPDATEDBY><![CDATA[0]]></UPDATEDBY>
  <C_ORDER_ID><![CDATA[7C2E2D10ECD443E5A49EE13EF9B1ADEC]]></C_ORDER_ID>
  <DUEDATE><![CDATA[2012-07-24 00:00:00.0]]></DUEDATE>
  <FIN_PAYMENTMETHOD_ID><![CDATA[45A202BF44884F05B8A1BF741E2063B6]]></FIN_PAYMENTMETHOD_ID>
  <C_CURRENCY_ID><![CDATA[102]]></C_CURRENCY_ID>
  <AMOUNT><![CDATA[8.64]]></AMOUNT>
  <PAIDAMT><![CDATA[8.64]]></PAIDAMT>
  <OUTSTANDINGAMT><![CDATA[0.00]]></OUTSTANDINGAMT>
  <ISACTIVE><![CDATA[Y]]></ISACTIVE>
  <UPDATE_PAYMENT_PLAN><![CDATA[Y]]></UPDATE_PAYMENT_PLAN>
  <EXPECTEDDATE><![CDATA[2012-07-24 00:00:00.0]]></EXPECTEDDATE>
  <EM_APRM_MODIF_PAYM_SCHED><![CDATA[N]]></EM_APRM_MODIF_PAYM_SCHED>
  <EM_APRM_MODIF_PAYM_OUT_SCHED><![CDATA[N]]></EM_APRM_MODIF_PAYM_OUT_SCHED>
</FIN_PAYMENT_SCHEDULE>

<FIN_PAYMENT_SCHEDULE>
  <FIN_PAYMENT_SCHEDULE_ID><![CDATA[31056249BF5D42A5A7F99541483F2819]]></FIN_PAYMENT_SCHEDULE_ID>
  <AD_CLIENT_ID><![CDATA[39363B0921BB4293B48383844325E84C]]></AD_CLIENT_ID>
  <AD_ORG_ID><![CDATA[D270A5AC50874F8BA67A88EE977F8E3B]]></AD_ORG_ID>
  <CREATED><![CDATA[2013-07-04 23:01:16.7]]></CREATED>
  <CREATEDBY><![CDATA[0]]></CREATEDBY>
  <UPDATED><![CDATA[2013-07-04 23:01:16.7]]></UPDATED>
  <UPDATEDBY><![CDATA[0]]></UPDATEDBY>
  <C_ORDER_ID><![CDATA[183284C25ADF2C86284B7D3D4260C151]]></C_ORDER_ID>
  <DUEDATE><![CDATA[2013-03-01 00:00:00.0]]></DUEDATE>
  <FIN_PAYMENTMETHOD_ID><![CDATA[45A202BF44884F05B8A1BF741E2063B6]]></FIN_PAYMENTMETHOD_ID>
  <C_CURRENCY_ID><![CDATA[102]]></C_CURRENCY_ID>
  <AMOUNT><![CDATA[174.80]]></AMOUNT>
  <PAIDAMT><![CDATA[174.80]]></PAIDAMT>
  <OUTSTANDINGAMT><![CDATA[0.00]]></OUTSTANDINGAMT>
  <ISACTIVE><![CDATA[Y]]></ISACTIVE>
  <UPDATE_PAYMENT_PLAN><![CDATA[Y]]></UPDATE_PAYMENT_PLAN>
  <EXPECTEDDATE><![CDATA[2013-03-01 00:00:00.0]]></EXPECTEDDATE>
  <EM_APRM_MODIF_PAYM_SCHED><![CDATA[N]]></EM_APRM_MODIF_PAYM_SCHED>
  <EM_APRM_MODIF_PAYM_OUT_SCHED><![CDATA[N]]></EM_APRM_MODIF_PAYM_OUT_SCHED>
</FIN_PAYMENT_SCHEDULE>

<FIN_PAYMENT_SCHEDULE>
  <FIN_PAYMENT_SCHEDULE_ID><![CDATA[353D3F4344364D56BB0AD89BDEC95E06]]></FIN_PAYMENT_SCHEDULE_ID>
  <AD_CLIENT_ID><![CDATA[39363B0921BB4293B48383844325E84C]]></AD_CLIENT_ID>
  <AD_ORG_ID><![CDATA[D270A5AC50874F8BA67A88EE977F8E3B]]></AD_ORG_ID>
  <CREATED><![CDATA[2014-04-19 20:31:34.613]]></CREATED>
  <CREATEDBY><![CDATA[3073EDF96A3C42CC86C7069E379522D2]]></CREATEDBY>
  <UPDATED><![CDATA[2014-04-19 20:31:34.933]]></UPDATED>
  <UPDATEDBY><![CDATA[3073EDF96A3C42CC86C7069E379522D2]]></UPDATEDBY>
  <C_ORDER_ID><![CDATA[90B111F35A6BF48C964139D0C1B5A8B3]]></C_ORDER_ID>
  <DUEDATE><![CDATA[2014-04-19 00:00:00.0]]></DUEDATE>
  <FIN_PAYMENTMETHOD_ID><![CDATA[45A202BF44884F05B8A1BF741E2063B6]]></FIN_PAYMENTMETHOD_ID>
  <C_CURRENCY_ID><![CDATA[102]]></C_CURRENCY_ID>
  <AMOUNT><![CDATA[54.50]]></AMOUNT>
  <PAIDAMT><![CDATA[54.50]]></PAIDAMT>
  <OUTSTANDINGAMT><![CDATA[0.00]]></OUTSTANDINGAMT>
  <ISACTIVE><![CDATA[Y]]></ISACTIVE>
  <UPDATE_PAYMENT_PLAN><![CDATA[Y]]></UPDATE_PAYMENT_PLAN>
  <EXPECTEDDATE><![CDATA[2014-04-19 00:00:00.0]]></EXPECTEDDATE>
  <EM_APRM_MODIF_PAYM_SCHED><![CDATA[N]]></EM_APRM_MODIF_PAYM_SCHED>
  <EM_APRM_MODIF_PAYM_OUT_SCHED><![CDATA[N]]></EM_APRM_MODIF_PAYM_OUT_SCHED>
</FIN_PAYMENT_SCHEDULE>

<FIN_PAYMENT_SCHEDULE>
  <FIN_PAYMENT_SCHEDULE_ID><![CDATA[3AEB3BD3C2CB40FCBAABBCDDF0473073]]></FIN_PAYMENT_SCHEDULE_ID>
  <AD_CLIENT_ID><![CDATA[39363B0921BB4293B48383844325E84C]]></AD_CLIENT_ID>
  <AD_ORG_ID><![CDATA[D270A5AC50874F8BA67A88EE977F8E3B]]></AD_ORG_ID>
  <CREATED><![CDATA[2014-04-19 20:35:32.351]]></CREATED>
  <CREATEDBY><![CDATA[3073EDF96A3C42CC86C7069E379522D2]]></CREATEDBY>
  <UPDATED><![CDATA[2014-04-19 20:35:32.536]]></UPDATED>
  <UPDATEDBY><![CDATA[3073EDF96A3C42CC86C7069E379522D2]]></UPDATEDBY>
  <C_INVOICE_ID><![CDATA[79D054EFBB39487E9F1F87E341148BE7]]></C_INVOICE_ID>
  <DUEDATE><![CDATA[2014-04-19 20:35:31.0]]></DUEDATE>
  <FIN_PAYMENTMETHOD_ID><![CDATA[45A202BF44884F05B8A1BF741E2063B6]]></FIN_PAYMENTMETHOD_ID>
  <C_CURRENCY_ID><![CDATA[102]]></C_CURRENCY_ID>
  <AMOUNT><![CDATA[54.50]]></AMOUNT>
  <PAIDAMT><![CDATA[54.50]]></PAIDAMT>
  <OUTSTANDINGAMT><![CDATA[0]]></OUTSTANDINGAMT>
  <ISACTIVE><![CDATA[Y]]></ISACTIVE>
  <UPDATE_PAYMENT_PLAN><![CDATA[Y]]></UPDATE_PAYMENT_PLAN>
  <EXPECTEDDATE><![CDATA[2014-04-19 20:35:31.0]]></EXPECTEDDATE>
  <EM_APRM_MODIF_PAYM_SCHED><![CDATA[N]]></EM_APRM_MODIF_PAYM_SCHED>
  <EM_APRM_MODIF_PAYM_OUT_SCHED><![CDATA[N]]></EM_APRM_MODIF_PAYM_OUT_SCHED>
</FIN_PAYMENT_SCHEDULE>

<FIN_PAYMENT_SCHEDULE>
  <FIN_PAYMENT_SCHEDULE_ID><![CDATA[406E28E553A949D4A86F9ED87B7EAD82]]></FIN_PAYMENT_SCHEDULE_ID>
  <AD_CLIENT_ID><![CDATA[39363B0921BB4293B48383844325E84C]]></AD_CLIENT_ID>
  <AD_ORG_ID><![CDATA[D270A5AC50874F8BA67A88EE977F8E3B]]></AD_ORG_ID>
  <CREATED><![CDATA[2013-07-04 23:01:16.702]]></CREATED>
  <CREATEDBY><![CDATA[0]]></CREATEDBY>
  <UPDATED><![CDATA[2013-07-04 23:01:16.702]]></UPDATED>
  <UPDATEDBY><![CDATA[0]]></UPDATEDBY>
  <C_ORDER_ID><![CDATA[FB0662A0C7764A6185FEF94EFB359891]]></C_ORDER_ID>
  <DUEDATE><![CDATA[2012-07-24 00:00:00.0]]></DUEDATE>
  <FIN_PAYMENTMETHOD_ID><![CDATA[45A202BF44884F05B8A1BF741E2063B6]]></FIN_PAYMENTMETHOD_ID>
  <C_CURRENCY_ID><![CDATA[102]]></C_CURRENCY_ID>
  <AMOUNT><![CDATA[63.4]]></AMOUNT>
  <PAIDAMT><![CDATA[63.4]]></PAIDAMT>
  <OUTSTANDINGAMT><![CDATA[0.0]]></OUTSTANDINGAMT>
  <ISACTIVE><![CDATA[Y]]></ISACTIVE>
  <UPDATE_PAYMENT_PLAN><![CDATA[Y]]></UPDATE_PAYMENT_PLAN>
  <EXPECTEDDATE><![CDATA[2012-07-24 00:00:00.0]]></EXPECTEDDATE>
  <EM_APRM_MODIF_PAYM_SCHED><![CDATA[N]]></EM_APRM_MODIF_PAYM_SCHED>
  <EM_APRM_MODIF_PAYM_OUT_SCHED><![CDATA[N]]></EM_APRM_MODIF_PAYM_OUT_SCHED>
</FIN_PAYMENT_SCHEDULE>

<FIN_PAYMENT_SCHEDULE>
  <FIN_PAYMENT_SCHEDULE_ID><![CDATA[4477FF4923A44C689739A8B1FF0D179B]]></FIN_PAYMENT_SCHEDULE_ID>
  <AD_CLIENT_ID><![CDATA[39363B0921BB4293B48383844325E84C]]></AD_CLIENT_ID>
  <AD_ORG_ID><![CDATA[3B187EC130A549A7A9388F8060EF156D]]></AD_ORG_ID>
  <CREATED><![CDATA[2013-07-04 23:01:16.7]]></CREATED>
  <CREATEDBY><![CDATA[0]]></CREATEDBY>
  <UPDATED><![CDATA[2013-07-04 23:01:16.7]]></UPDATED>
  <UPDATEDBY><![CDATA[0]]></UPDATEDBY>
  <C_ORDER_ID><![CDATA[4EBC6126561749488DBC1122C57A14C3]]></C_ORDER_ID>
  <DUEDATE><![CDATA[2012-07-24 00:00:00.0]]></DUEDATE>
  <FIN_PAYMENTMETHOD_ID><![CDATA[45A202BF44884F05B8A1BF741E2063B6]]></FIN_PAYMENTMETHOD_ID>
  <C_CURRENCY_ID><![CDATA[102]]></C_CURRENCY_ID>
  <AMOUNT><![CDATA[276.9]]></AMOUNT>
  <PAIDAMT><![CDATA[276.9]]></PAIDAMT>
  <OUTSTANDINGAMT><![CDATA[0.0]]></OUTSTANDINGAMT>
  <ISACTIVE><![CDATA[Y]]></ISACTIVE>
  <UPDATE_PAYMENT_PLAN><![CDATA[Y]]></UPDATE_PAYMENT_PLAN>
  <EXPECTEDDATE><![CDATA[2012-07-24 00:00:00.0]]></EXPECTEDDATE>
  <EM_APRM_MODIF_PAYM_SCHED><![CDATA[N]]></EM_APRM_MODIF_PAYM_SCHED>
  <EM_APRM_MODIF_PAYM_OUT_SCHED><![CDATA[N]]></EM_APRM_MODIF_PAYM_OUT_SCHED>
</FIN_PAYMENT_SCHEDULE>

<FIN_PAYMENT_SCHEDULE>
  <FIN_PAYMENT_SCHEDULE_ID><![CDATA[47DF3C8B3E4A4A7AB0607DBE9FF2641F]]></FIN_PAYMENT_SCHEDULE_ID>
  <AD_CLIENT_ID><![CDATA[39363B0921BB4293B48383844325E84C]]></AD_CLIENT_ID>
  <AD_ORG_ID><![CDATA[3B187EC130A549A7A9388F8060EF156D]]></AD_ORG_ID>
  <CREATED><![CDATA[2013-07-04 23:01:16.699]]></CREATED>
  <CREATEDBY><![CDATA[0]]></CREATEDBY>
  <UPDATED><![CDATA[2013-07-04 23:01:16.699]]></UPDATED>
  <UPDATEDBY><![CDATA[0]]></UPDATEDBY>
  <C_ORDER_ID><![CDATA[1043BA348CCD4593856B47535B619CF4]]></C_ORDER_ID>
  <DUEDATE><![CDATA[2012-07-24 00:00:00.0]]></DUEDATE>
  <FIN_PAYMENTMETHOD_ID><![CDATA[45A202BF44884F05B8A1BF741E2063B6]]></FIN_PAYMENTMETHOD_ID>
  <C_CURRENCY_ID><![CDATA[102]]></C_CURRENCY_ID>
  <AMOUNT><![CDATA[216.0]]></AMOUNT>
  <PAIDAMT><![CDATA[216.0]]></PAIDAMT>
  <OUTSTANDINGAMT><![CDATA[0.0]]></OUTSTANDINGAMT>
  <ISACTIVE><![CDATA[Y]]></ISACTIVE>
  <UPDATE_PAYMENT_PLAN><![CDATA[Y]]></UPDATE_PAYMENT_PLAN>
  <EXPECTEDDATE><![CDATA[2012-07-24 00:00:00.0]]></EXPECTEDDATE>
  <EM_APRM_MODIF_PAYM_SCHED><![CDATA[N]]></EM_APRM_MODIF_PAYM_SCHED>
  <EM_APRM_MODIF_PAYM_OUT_SCHED><![CDATA[N]]></EM_APRM_MODIF_PAYM_OUT_SCHED>
</FIN_PAYMENT_SCHEDULE>

<FIN_PAYMENT_SCHEDULE>
  <FIN_PAYMENT_SCHEDULE_ID><![CDATA[4AE328FFD53C451EA62F602F50993A23]]></FIN_PAYMENT_SCHEDULE_ID>
  <AD_CLIENT_ID><![CDATA[39363B0921BB4293B48383844325E84C]]></AD_CLIENT_ID>
  <AD_ORG_ID><![CDATA[3B187EC130A549A7A9388F8060EF156D]]></AD_ORG_ID>
  <CREATED><![CDATA[2013-07-04 23:01:16.699]]></CREATED>
  <CREATEDBY><![CDATA[0]]></CREATEDBY>
  <UPDATED><![CDATA[2013-07-04 23:01:16.699]]></UPDATED>
  <UPDATEDBY><![CDATA[0]]></UPDATEDBY>
  <C_ORDER_ID><![CDATA[C5F52DD1DFB04BB0A193F562EA6373DD]]></C_ORDER_ID>
  <DUEDATE><![CDATA[2012-07-24 00:00:00.0]]></DUEDATE>
  <FIN_PAYMENTMETHOD_ID><![CDATA[45A202BF44884F05B8A1BF741E2063B6]]></FIN_PAYMENTMETHOD_ID>
  <C_CURRENCY_ID><![CDATA[102]]></C_CURRENCY_ID>
  <AMOUNT><![CDATA[699.8]]></AMOUNT>
  <PAIDAMT><![CDATA[699.8]]></PAIDAMT>
  <OUTSTANDINGAMT><![CDATA[0.0]]></OUTSTANDINGAMT>
  <ISACTIVE><![CDATA[Y]]></ISACTIVE>
  <UPDATE_PAYMENT_PLAN><![CDATA[Y]]></UPDATE_PAYMENT_PLAN>
  <EXPECTEDDATE><![CDATA[2012-07-24 00:00:00.0]]></EXPECTEDDATE>
  <EM_APRM_MODIF_PAYM_SCHED><![CDATA[N]]></EM_APRM_MODIF_PAYM_SCHED>
  <EM_APRM_MODIF_PAYM_OUT_SCHED><![CDATA[N]]></EM_APRM_MODIF_PAYM_OUT_SCHED>
</FIN_PAYMENT_SCHEDULE>

<FIN_PAYMENT_SCHEDULE>
  <FIN_PAYMENT_SCHEDULE_ID><![CDATA[4FB4C8121CF94FD7887E164085DCEAB0]]></FIN_PAYMENT_SCHEDULE_ID>
  <AD_CLIENT_ID><![CDATA[39363B0921BB4293B48383844325E84C]]></AD_CLIENT_ID>
  <AD_ORG_ID><![CDATA[3B187EC130A549A7A9388F8060EF156D]]></AD_ORG_ID>
  <CREATED><![CDATA[2014-04-19 20:38:15.33]]></CREATED>
  <CREATEDBY><![CDATA[1D0E5A14E65D474FA8EC8311E009E253]]></CREATEDBY>
  <UPDATED><![CDATA[2014-04-19 20:38:15.444]]></UPDATED>
  <UPDATEDBY><![CDATA[1D0E5A14E65D474FA8EC8311E009E253]]></UPDATEDBY>
  <C_ORDER_ID><![CDATA[3962218041805AD71EBA53CEEB9F779C]]></C_ORDER_ID>
  <DUEDATE><![CDATA[2014-04-19 00:00:00.0]]></DUEDATE>
  <FIN_PAYMENTMETHOD_ID><![CDATA[45A202BF44884F05B8A1BF741E2063B6]]></FIN_PAYMENTMETHOD_ID>
  <C_CURRENCY_ID><![CDATA[102]]></C_CURRENCY_ID>
  <AMOUNT><![CDATA[54.50]]></AMOUNT>
  <PAIDAMT><![CDATA[54.50]]></PAIDAMT>
  <OUTSTANDINGAMT><![CDATA[0.00]]></OUTSTANDINGAMT>
  <ISACTIVE><![CDATA[Y]]></ISACTIVE>
  <UPDATE_PAYMENT_PLAN><![CDATA[Y]]></UPDATE_PAYMENT_PLAN>
  <EXPECTEDDATE><![CDATA[2014-04-19 00:00:00.0]]></EXPECTEDDATE>
  <EM_APRM_MODIF_PAYM_SCHED><![CDATA[N]]></EM_APRM_MODIF_PAYM_SCHED>
  <EM_APRM_MODIF_PAYM_OUT_SCHED><![CDATA[N]]></EM_APRM_MODIF_PAYM_OUT_SCHED>
</FIN_PAYMENT_SCHEDULE>

<FIN_PAYMENT_SCHEDULE>
  <FIN_PAYMENT_SCHEDULE_ID><![CDATA[502D1ECAE53340079620176D628F178A]]></FIN_PAYMENT_SCHEDULE_ID>
  <AD_CLIENT_ID><![CDATA[39363B0921BB4293B48383844325E84C]]></AD_CLIENT_ID>
  <AD_ORG_ID><![CDATA[BF129721D9FB4EB0819509934153E972]]></AD_ORG_ID>
  <CREATED><![CDATA[2013-07-04 23:01:16.745]]></CREATED>
  <CREATEDBY><![CDATA[0]]></CREATEDBY>
  <UPDATED><![CDATA[2013-07-04 23:01:16.745]]></UPDATED>
  <UPDATEDBY><![CDATA[0]]></UPDATEDBY>
  <C_ORDER_ID><![CDATA[9FC0A724AE1741E2AC235042505A90B9]]></C_ORDER_ID>
  <DUEDATE><![CDATA[2012-07-06 00:00:00.0]]></DUEDATE>
  <FIN_PAYMENTMETHOD_ID><![CDATA[5A741F883A31408CA3AC097D76AA6D32]]></FIN_PAYMENTMETHOD_ID>
  <C_CURRENCY_ID><![CDATA[102]]></C_CURRENCY_ID>
  <AMOUNT><![CDATA[2100]]></AMOUNT>
  <PAIDAMT><![CDATA[0]]></PAIDAMT>
  <OUTSTANDINGAMT><![CDATA[2100]]></OUTSTANDINGAMT>
  <ISACTIVE><![CDATA[Y]]></ISACTIVE>
  <UPDATE_PAYMENT_PLAN><![CDATA[Y]]></UPDATE_PAYMENT_PLAN>
  <EXPECTEDDATE><![CDATA[2012-07-06 00:00:00.0]]></EXPECTEDDATE>
  <EM_APRM_MODIF_PAYM_SCHED><![CDATA[N]]></EM_APRM_MODIF_PAYM_SCHED>
  <EM_APRM_MODIF_PAYM_OUT_SCHED><![CDATA[N]]></EM_APRM_MODIF_PAYM_OUT_SCHED>
</FIN_PAYMENT_SCHEDULE>

<FIN_PAYMENT_SCHEDULE>
  <FIN_PAYMENT_SCHEDULE_ID><![CDATA[571105FAD8EC420888922F2E9DA45478]]></FIN_PAYMENT_SCHEDULE_ID>
  <AD_CLIENT_ID><![CDATA[39363B0921BB4293B48383844325E84C]]></AD_CLIENT_ID>
  <AD_ORG_ID><![CDATA[D270A5AC50874F8BA67A88EE977F8E3B]]></AD_ORG_ID>
  <CREATED><![CDATA[2013-07-04 23:01:16.703]]></CREATED>
  <CREATEDBY><![CDATA[0]]></CREATEDBY>
  <UPDATED><![CDATA[2013-07-04 23:01:16.703]]></UPDATED>
  <UPDATEDBY><![CDATA[0]]></UPDATEDBY>
  <C_ORDER_ID><![CDATA[DBCFE20D6AA84BB78B4B9D5A84A0C899]]></C_ORDER_ID>
  <DUEDATE><![CDATA[2012-07-24 00:00:00.0]]></DUEDATE>
  <FIN_PAYMENTMETHOD_ID><![CDATA[45A202BF44884F05B8A1BF741E2063B6]]></FIN_PAYMENTMETHOD_ID>
  <C_CURRENCY_ID><![CDATA[102]]></C_CURRENCY_ID>
  <AMOUNT><![CDATA[3.6]]></AMOUNT>
  <PAIDAMT><![CDATA[3.6]]></PAIDAMT>
  <OUTSTANDINGAMT><![CDATA[0.0]]></OUTSTANDINGAMT>
  <ISACTIVE><![CDATA[Y]]></ISACTIVE>
  <UPDATE_PAYMENT_PLAN><![CDATA[Y]]></UPDATE_PAYMENT_PLAN>
  <EXPECTEDDATE><![CDATA[2012-07-24 00:00:00.0]]></EXPECTEDDATE>
  <EM_APRM_MODIF_PAYM_SCHED><![CDATA[N]]></EM_APRM_MODIF_PAYM_SCHED>
  <EM_APRM_MODIF_PAYM_OUT_SCHED><![CDATA[N]]></EM_APRM_MODIF_PAYM_OUT_SCHED>
</FIN_PAYMENT_SCHEDULE>

<FIN_PAYMENT_SCHEDULE>
  <FIN_PAYMENT_SCHEDULE_ID><![CDATA[571C1D0C81DF4454A267273D2E6ECFD9]]></FIN_PAYMENT_SCHEDULE_ID>
  <AD_CLIENT_ID><![CDATA[39363B0921BB4293B48383844325E84C]]></AD_CLIENT_ID>
  <AD_ORG_ID><![CDATA[D270A5AC50874F8BA67A88EE977F8E3B]]></AD_ORG_ID>
  <CREATED><![CDATA[2013-11-27 01:20:23.093]]></CREATED>
  <CREATEDBY><![CDATA[E49545E7D0A2413E90C31C2CDC2153B1]]></CREATEDBY>
  <UPDATED><![CDATA[2013-11-27 01:20:23.277]]></UPDATED>
  <UPDATEDBY><![CDATA[E49545E7D0A2413E90C31C2CDC2153B1]]></UPDATEDBY>
  <C_INVOICE_ID><![CDATA[E65EBB56577147659B39BA447B46329A]]></C_INVOICE_ID>
  <DUEDATE><![CDATA[2013-11-27 01:20:23.084]]></DUEDATE>
  <FIN_PAYMENTMETHOD_ID><![CDATA[45A202BF44884F05B8A1BF741E2063B6]]></FIN_PAYMENTMETHOD_ID>
  <C_CURRENCY_ID><![CDATA[102]]></C_CURRENCY_ID>
  <AMOUNT><![CDATA[2310.60]]></AMOUNT>
  <PAIDAMT><![CDATA[2310.60]]></PAIDAMT>
  <OUTSTANDINGAMT><![CDATA[0]]></OUTSTANDINGAMT>
  <ISACTIVE><![CDATA[Y]]></ISACTIVE>
  <UPDATE_PAYMENT_PLAN><![CDATA[Y]]></UPDATE_PAYMENT_PLAN>
  <EXPECTEDDATE><![CDATA[2013-11-27 01:20:23.084]]></EXPECTEDDATE>
  <EM_APRM_MODIF_PAYM_SCHED><![CDATA[N]]></EM_APRM_MODIF_PAYM_SCHED>
  <EM_APRM_MODIF_PAYM_OUT_SCHED><![CDATA[N]]></EM_APRM_MODIF_PAYM_OUT_SCHED>
</FIN_PAYMENT_SCHEDULE>

<FIN_PAYMENT_SCHEDULE>
  <FIN_PAYMENT_SCHEDULE_ID><![CDATA[666828CC49364AFE863A19750F7D075C]]></FIN_PAYMENT_SCHEDULE_ID>
  <AD_CLIENT_ID><![CDATA[39363B0921BB4293B48383844325E84C]]></AD_CLIENT_ID>
  <AD_ORG_ID><![CDATA[01AD882EFC8545ACA6455E2F6FD51EE9]]></AD_ORG_ID>
  <CREATED><![CDATA[2013-07-04 23:01:16.745]]></CREATED>
  <CREATEDBY><![CDATA[0]]></CREATEDBY>
  <UPDATED><![CDATA[2013-07-04 23:01:16.745]]></UPDATED>
  <UPDATEDBY><![CDATA[0]]></UPDATEDBY>
  <C_ORDER_ID><![CDATA[7B553C9CBBC14FA4917C421C5DD24F53]]></C_ORDER_ID>
  <DUEDATE><![CDATA[2012-07-08 00:00:00.0]]></DUEDATE>
  <FIN_PAYMENTMETHOD_ID><![CDATA[5A741F883A31408CA3AC097D76AA6D32]]></FIN_PAYMENTMETHOD_ID>
  <C_CURRENCY_ID><![CDATA[102]]></C_CURRENCY_ID>
  <AMOUNT><![CDATA[1389370.40]]></AMOUNT>
  <PAIDAMT><![CDATA[0]]></PAIDAMT>
  <OUTSTANDINGAMT><![CDATA[1389370.40]]></OUTSTANDINGAMT>
  <ISACTIVE><![CDATA[Y]]></ISACTIVE>
  <UPDATE_PAYMENT_PLAN><![CDATA[Y]]></UPDATE_PAYMENT_PLAN>
  <EXPECTEDDATE><![CDATA[2012-07-08 00:00:00.0]]></EXPECTEDDATE>
  <EM_APRM_MODIF_PAYM_SCHED><![CDATA[N]]></EM_APRM_MODIF_PAYM_SCHED>
  <EM_APRM_MODIF_PAYM_OUT_SCHED><![CDATA[N]]></EM_APRM_MODIF_PAYM_OUT_SCHED>
</FIN_PAYMENT_SCHEDULE>

<FIN_PAYMENT_SCHEDULE>
  <FIN_PAYMENT_SCHEDULE_ID><![CDATA[66FAE4048A0749B69083A403FF472FE2]]></FIN_PAYMENT_SCHEDULE_ID>
  <AD_CLIENT_ID><![CDATA[39363B0921BB4293B48383844325E84C]]></AD_CLIENT_ID>
  <AD_ORG_ID><![CDATA[D270A5AC50874F8BA67A88EE977F8E3B]]></AD_ORG_ID>
  <CREATED><![CDATA[2014-04-22 15:57:33.984]]></CREATED>
  <CREATEDBY><![CDATA[3073EDF96A3C42CC86C7069E379522D2]]></CREATEDBY>
  <UPDATED><![CDATA[2014-04-22 15:57:34.097]]></UPDATED>
  <UPDATEDBY><![CDATA[3073EDF96A3C42CC86C7069E379522D2]]></UPDATEDBY>
  <C_ORDER_ID><![CDATA[068DCCBCB90F80C459DD7BA46E32C16B]]></C_ORDER_ID>
  <DUEDATE><![CDATA[2014-04-22 00:00:00.0]]></DUEDATE>
  <FIN_PAYMENTMETHOD_ID><![CDATA[45A202BF44884F05B8A1BF741E2063B6]]></FIN_PAYMENTMETHOD_ID>
  <C_CURRENCY_ID><![CDATA[102]]></C_CURRENCY_ID>
  <AMOUNT><![CDATA[203.50]]></AMOUNT>
  <PAIDAMT><![CDATA[203.50]]></PAIDAMT>
  <OUTSTANDINGAMT><![CDATA[0.00]]></OUTSTANDINGAMT>
  <ISACTIVE><![CDATA[Y]]></ISACTIVE>
  <UPDATE_PAYMENT_PLAN><![CDATA[Y]]></UPDATE_PAYMENT_PLAN>
  <EXPECTEDDATE><![CDATA[2014-04-22 00:00:00.0]]></EXPECTEDDATE>
  <EM_APRM_MODIF_PAYM_SCHED><![CDATA[N]]></EM_APRM_MODIF_PAYM_SCHED>
  <EM_APRM_MODIF_PAYM_OUT_SCHED><![CDATA[N]]></EM_APRM_MODIF_PAYM_OUT_SCHED>
</FIN_PAYMENT_SCHEDULE>

<FIN_PAYMENT_SCHEDULE>
  <FIN_PAYMENT_SCHEDULE_ID><![CDATA[6DEA87F402914201A006667032B3E939]]></FIN_PAYMENT_SCHEDULE_ID>
  <AD_CLIENT_ID><![CDATA[39363B0921BB4293B48383844325E84C]]></AD_CLIENT_ID>
  <AD_ORG_ID><![CDATA[D270A5AC50874F8BA67A88EE977F8E3B]]></AD_ORG_ID>
  <CREATED><![CDATA[2013-07-04 23:01:16.745]]></CREATED>
  <CREATEDBY><![CDATA[0]]></CREATEDBY>
  <UPDATED><![CDATA[2013-07-04 23:01:16.745]]></UPDATED>
  <UPDATEDBY><![CDATA[0]]></UPDATEDBY>
  <C_ORDER_ID><![CDATA[AD197568A4134CA550341653CC8583EF]]></C_ORDER_ID>
  <DUEDATE><![CDATA[2013-03-01 00:00:00.0]]></DUEDATE>
  <FIN_PAYMENTMETHOD_ID><![CDATA[45A202BF44884F05B8A1BF741E2063B6]]></FIN_PAYMENTMETHOD_ID>
  <C_CURRENCY_ID><![CDATA[102]]></C_CURRENCY_ID>
  <AMOUNT><![CDATA[0]]></AMOUNT>
  <PAIDAMT><![CDATA[0]]></PAIDAMT>
  <OUTSTANDINGAMT><![CDATA[0]]></OUTSTANDINGAMT>
  <ISACTIVE><![CDATA[Y]]></ISACTIVE>
  <UPDATE_PAYMENT_PLAN><![CDATA[Y]]></UPDATE_PAYMENT_PLAN>
  <EXPECTEDDATE><![CDATA[2013-03-01 00:00:00.0]]></EXPECTEDDATE>
  <EM_APRM_MODIF_PAYM_SCHED><![CDATA[N]]></EM_APRM_MODIF_PAYM_SCHED>
  <EM_APRM_MODIF_PAYM_OUT_SCHED><![CDATA[N]]></EM_APRM_MODIF_PAYM_OUT_SCHED>
</FIN_PAYMENT_SCHEDULE>

<FIN_PAYMENT_SCHEDULE>
  <FIN_PAYMENT_SCHEDULE_ID><![CDATA[7085D398ACF34801A16DCBAC0B815C22]]></FIN_PAYMENT_SCHEDULE_ID>
  <AD_CLIENT_ID><![CDATA[39363B0921BB4293B48383844325E84C]]></AD_CLIENT_ID>
  <AD_ORG_ID><![CDATA[D270A5AC50874F8BA67A88EE977F8E3B]]></AD_ORG_ID>
  <CREATED><![CDATA[2013-07-04 23:01:16.699]]></CREATED>
  <CREATEDBY><![CDATA[0]]></CREATEDBY>
  <UPDATED><![CDATA[2013-07-04 23:01:16.699]]></UPDATED>
  <UPDATEDBY><![CDATA[0]]></UPDATEDBY>
  <C_INVOICE_ID><![CDATA[14E471C408F94436AC8B62DA8E2F60AA]]></C_INVOICE_ID>
  <DUEDATE><![CDATA[2012-07-24 12:22:28.208]]></DUEDATE>
  <FIN_PAYMENTMETHOD_ID><![CDATA[45A202BF44884F05B8A1BF741E2063B6]]></FIN_PAYMENTMETHOD_ID>
  <C_CURRENCY_ID><![CDATA[102]]></C_CURRENCY_ID>
  <AMOUNT><![CDATA[823.1]]></AMOUNT>
  <PAIDAMT><![CDATA[823.1]]></PAIDAMT>
  <OUTSTANDINGAMT><![CDATA[0]]></OUTSTANDINGAMT>
  <ISACTIVE><![CDATA[Y]]></ISACTIVE>
  <UPDATE_PAYMENT_PLAN><![CDATA[Y]]></UPDATE_PAYMENT_PLAN>
  <EXPECTEDDATE><![CDATA[2012-07-24 12:22:28.208]]></EXPECTEDDATE>
  <EM_APRM_MODIF_PAYM_SCHED><![CDATA[N]]></EM_APRM_MODIF_PAYM_SCHED>
  <EM_APRM_MODIF_PAYM_OUT_SCHED><![CDATA[N]]></EM_APRM_MODIF_PAYM_OUT_SCHED>
</FIN_PAYMENT_SCHEDULE>

<FIN_PAYMENT_SCHEDULE>
  <FIN_PAYMENT_SCHEDULE_ID><![CDATA[71FDDEC4B3A84C6997AC4429518092CE]]></FIN_PAYMENT_SCHEDULE_ID>
  <AD_CLIENT_ID><![CDATA[39363B0921BB4293B48383844325E84C]]></AD_CLIENT_ID>
  <AD_ORG_ID><![CDATA[D270A5AC50874F8BA67A88EE977F8E3B]]></AD_ORG_ID>
  <CREATED><![CDATA[2013-07-04 23:01:16.744]]></CREATED>
  <CREATEDBY><![CDATA[0]]></CREATEDBY>
  <UPDATED><![CDATA[2013-07-04 23:01:16.744]]></UPDATED>
  <UPDATEDBY><![CDATA[0]]></UPDATEDBY>
  <C_ORDER_ID><![CDATA[B28B90BA6BD12AC8EF87B4A1AB71055B]]></C_ORDER_ID>
  <DUEDATE><![CDATA[2013-03-01 00:00:00.0]]></DUEDATE>
  <FIN_PAYMENTMETHOD_ID><![CDATA[45A202BF44884F05B8A1BF741E2063B6]]></FIN_PAYMENTMETHOD_ID>
  <C_CURRENCY_ID><![CDATA[102]]></C_CURRENCY_ID>
  <AMOUNT><![CDATA[401.70]]></AMOUNT>
  <PAIDAMT><![CDATA[80.00]]></PAIDAMT>
  <OUTSTANDINGAMT><![CDATA[321.70]]></OUTSTANDINGAMT>
  <ISACTIVE><![CDATA[Y]]></ISACTIVE>
  <UPDATE_PAYMENT_PLAN><![CDATA[Y]]></UPDATE_PAYMENT_PLAN>
  <EXPECTEDDATE><![CDATA[2013-03-01 00:00:00.0]]></EXPECTEDDATE>
  <EM_APRM_MODIF_PAYM_SCHED><![CDATA[N]]></EM_APRM_MODIF_PAYM_SCHED>
  <EM_APRM_MODIF_PAYM_OUT_SCHED><![CDATA[N]]></EM_APRM_MODIF_PAYM_OUT_SCHED>
</FIN_PAYMENT_SCHEDULE>

<FIN_PAYMENT_SCHEDULE>
  <FIN_PAYMENT_SCHEDULE_ID><![CDATA[744A82C11EB543FBBE61408BABDBF6DB]]></FIN_PAYMENT_SCHEDULE_ID>
  <AD_CLIENT_ID><![CDATA[39363B0921BB4293B48383844325E84C]]></AD_CLIENT_ID>
  <AD_ORG_ID><![CDATA[B5DE96143D6642228E3B9DEC69886A47]]></AD_ORG_ID>
  <CREATED><![CDATA[2013-07-04 23:01:16.701]]></CREATED>
  <CREATEDBY><![CDATA[0]]></CREATEDBY>
  <UPDATED><![CDATA[2013-07-04 23:01:16.701]]></UPDATED>
  <UPDATEDBY><![CDATA[0]]></UPDATEDBY>
  <C_INVOICE_ID><![CDATA[BD360CE14B9945DC9334D8D352A9807E]]></C_INVOICE_ID>
  <DUEDATE><![CDATA[2012-07-24 14:12:30.18]]></DUEDATE>
  <FIN_PAYMENTMETHOD_ID><![CDATA[45A202BF44884F05B8A1BF741E2063B6]]></FIN_PAYMENTMETHOD_ID>
  <C_CURRENCY_ID><![CDATA[102]]></C_CURRENCY_ID>
  <AMOUNT><![CDATA[206.64]]></AMOUNT>
  <PAIDAMT><![CDATA[206.64]]></PAIDAMT>
  <OUTSTANDINGAMT><![CDATA[0]]></OUTSTANDINGAMT>
  <ISACTIVE><![CDATA[Y]]></ISACTIVE>
  <UPDATE_PAYMENT_PLAN><![CDATA[Y]]></UPDATE_PAYMENT_PLAN>
  <EXPECTEDDATE><![CDATA[2012-07-24 14:12:30.18]]></EXPECTEDDATE>
  <EM_APRM_MODIF_PAYM_SCHED><![CDATA[N]]></EM_APRM_MODIF_PAYM_SCHED>
  <EM_APRM_MODIF_PAYM_OUT_SCHED><![CDATA[N]]></EM_APRM_MODIF_PAYM_OUT_SCHED>
</FIN_PAYMENT_SCHEDULE>

<FIN_PAYMENT_SCHEDULE>
  <FIN_PAYMENT_SCHEDULE_ID><![CDATA[75D0E3AA26144054BBD3DF59131A70B4]]></FIN_PAYMENT_SCHEDULE_ID>
  <AD_CLIENT_ID><![CDATA[39363B0921BB4293B48383844325E84C]]></AD_CLIENT_ID>
  <AD_ORG_ID><![CDATA[D270A5AC50874F8BA67A88EE977F8E3B]]></AD_ORG_ID>
  <CREATED><![CDATA[2014-04-22 15:47:05.92]]></CREATED>
  <CREATEDBY><![CDATA[3073EDF96A3C42CC86C7069E379522D2]]></CREATEDBY>
  <UPDATED><![CDATA[2014-04-22 15:47:06.53]]></UPDATED>
  <UPDATEDBY><![CDATA[3073EDF96A3C42CC86C7069E379522D2]]></UPDATEDBY>
  <C_ORDER_ID><![CDATA[73157B1AFAF0C74213F9D7E82C79A50C]]></C_ORDER_ID>
  <DUEDATE><![CDATA[2014-04-22 00:00:00.0]]></DUEDATE>
  <FIN_PAYMENTMETHOD_ID><![CDATA[45A202BF44884F05B8A1BF741E2063B6]]></FIN_PAYMENTMETHOD_ID>
  <C_CURRENCY_ID><![CDATA[102]]></C_CURRENCY_ID>
  <AMOUNT><![CDATA[109.00]]></AMOUNT>
  <PAIDAMT><![CDATA[109.00]]></PAIDAMT>
  <OUTSTANDINGAMT><![CDATA[0.00]]></OUTSTANDINGAMT>
  <ISACTIVE><![CDATA[Y]]></ISACTIVE>
  <UPDATE_PAYMENT_PLAN><![CDATA[Y]]></UPDATE_PAYMENT_PLAN>
  <EXPECTEDDATE><![CDATA[2014-04-22 00:00:00.0]]></EXPECTEDDATE>
  <EM_APRM_MODIF_PAYM_SCHED><![CDATA[N]]></EM_APRM_MODIF_PAYM_SCHED>
  <EM_APRM_MODIF_PAYM_OUT_SCHED><![CDATA[N]]></EM_APRM_MODIF_PAYM_OUT_SCHED>
</FIN_PAYMENT_SCHEDULE>

<FIN_PAYMENT_SCHEDULE>
  <FIN_PAYMENT_SCHEDULE_ID><![CDATA[7F8AE3685E67407BBED57571A1AD0CEC]]></FIN_PAYMENT_SCHEDULE_ID>
  <AD_CLIENT_ID><![CDATA[39363B0921BB4293B48383844325E84C]]></AD_CLIENT_ID>
  <AD_ORG_ID><![CDATA[D270A5AC50874F8BA67A88EE977F8E3B]]></AD_ORG_ID>
  <CREATED><![CDATA[2014-04-19 20:27:17.0]]></CREATED>
  <CREATEDBY><![CDATA[100]]></CREATEDBY>
  <UPDATED><![CDATA[2014-04-19 20:27:17.0]]></UPDATED>
  <UPDATEDBY><![CDATA[100]]></UPDATEDBY>
  <C_ORDER_ID><![CDATA[5C15417613CF4A30B8EEEB86D71EBE97]]></C_ORDER_ID>
  <DUEDATE><![CDATA[2014-04-19 00:00:00.0]]></DUEDATE>
  <FIN_PAYMENTMETHOD_ID><![CDATA[5A741F883A31408CA3AC097D76AA6D32]]></FIN_PAYMENTMETHOD_ID>
  <C_CURRENCY_ID><![CDATA[102]]></C_CURRENCY_ID>
  <AMOUNT><![CDATA[76725.00]]></AMOUNT>
  <PAIDAMT><![CDATA[0]]></PAIDAMT>
  <OUTSTANDINGAMT><![CDATA[76725.00]]></OUTSTANDINGAMT>
  <ISACTIVE><![CDATA[Y]]></ISACTIVE>
  <UPDATE_PAYMENT_PLAN><![CDATA[Y]]></UPDATE_PAYMENT_PLAN>
  <EXPECTEDDATE><![CDATA[2014-04-19 00:00:00.0]]></EXPECTEDDATE>
  <EM_APRM_MODIF_PAYM_SCHED><![CDATA[N]]></EM_APRM_MODIF_PAYM_SCHED>
  <EM_APRM_MODIF_PAYM_OUT_SCHED><![CDATA[N]]></EM_APRM_MODIF_PAYM_OUT_SCHED>
</FIN_PAYMENT_SCHEDULE>

<FIN_PAYMENT_SCHEDULE>
  <FIN_PAYMENT_SCHEDULE_ID><![CDATA[813B7D43AA4A490F946331D9A424BBF7]]></FIN_PAYMENT_SCHEDULE_ID>
  <AD_CLIENT_ID><![CDATA[39363B0921BB4293B48383844325E84C]]></AD_CLIENT_ID>
  <AD_ORG_ID><![CDATA[3B187EC130A549A7A9388F8060EF156D]]></AD_ORG_ID>
  <CREATED><![CDATA[2013-07-04 23:01:16.699]]></CREATED>
  <CREATEDBY><![CDATA[0]]></CREATEDBY>
  <UPDATED><![CDATA[2013-07-04 23:01:16.699]]></UPDATED>
  <UPDATEDBY><![CDATA[0]]></UPDATEDBY>
  <C_INVOICE_ID><![CDATA[7FB6237496DA48C097993883957BEC16]]></C_INVOICE_ID>
  <DUEDATE><![CDATA[2012-07-24 12:45:20.277]]></DUEDATE>
  <FIN_PAYMENTMETHOD_ID><![CDATA[45A202BF44884F05B8A1BF741E2063B6]]></FIN_PAYMENTMETHOD_ID>
  <C_CURRENCY_ID><![CDATA[102]]></C_CURRENCY_ID>
  <AMOUNT><![CDATA[618.9]]></AMOUNT>
  <PAIDAMT><![CDATA[618.9]]></PAIDAMT>
  <OUTSTANDINGAMT><![CDATA[0]]></OUTSTANDINGAMT>
  <ISACTIVE><![CDATA[Y]]></ISACTIVE>
  <UPDATE_PAYMENT_PLAN><![CDATA[Y]]></UPDATE_PAYMENT_PLAN>
  <EXPECTEDDATE><![CDATA[2012-07-24 12:45:20.277]]></EXPECTEDDATE>
  <EM_APRM_MODIF_PAYM_SCHED><![CDATA[N]]></EM_APRM_MODIF_PAYM_SCHED>
  <EM_APRM_MODIF_PAYM_OUT_SCHED><![CDATA[N]]></EM_APRM_MODIF_PAYM_OUT_SCHED>
</FIN_PAYMENT_SCHEDULE>

<FIN_PAYMENT_SCHEDULE>
  <FIN_PAYMENT_SCHEDULE_ID><![CDATA[81BFA4A5E51A42DA91E86715ED2573F4]]></FIN_PAYMENT_SCHEDULE_ID>
  <AD_CLIENT_ID><![CDATA[39363B0921BB4293B48383844325E84C]]></AD_CLIENT_ID>
  <AD_ORG_ID><![CDATA[D270A5AC50874F8BA67A88EE977F8E3B]]></AD_ORG_ID>
  <CREATED><![CDATA[2013-07-04 23:01:16.699]]></CREATED>
  <CREATEDBY><![CDATA[0]]></CREATEDBY>
  <UPDATED><![CDATA[2013-07-04 23:01:16.699]]></UPDATED>
  <UPDATEDBY><![CDATA[0]]></UPDATEDBY>
  <C_ORDER_ID><![CDATA[93E33A707C76440E85D2DCE8689CF242]]></C_ORDER_ID>
  <DUEDATE><![CDATA[2012-07-22 00:00:00.0]]></DUEDATE>
  <FIN_PAYMENTMETHOD_ID><![CDATA[45A202BF44884F05B8A1BF741E2063B6]]></FIN_PAYMENTMETHOD_ID>
  <C_CURRENCY_ID><![CDATA[102]]></C_CURRENCY_ID>
  <AMOUNT><![CDATA[451.5]]></AMOUNT>
  <PAIDAMT><![CDATA[451.5]]></PAIDAMT>
  <OUTSTANDINGAMT><![CDATA[0.0]]></OUTSTANDINGAMT>
  <ISACTIVE><![CDATA[Y]]></ISACTIVE>
  <UPDATE_PAYMENT_PLAN><![CDATA[Y]]></UPDATE_PAYMENT_PLAN>
  <EXPECTEDDATE><![CDATA[2012-07-22 00:00:00.0]]></EXPECTEDDATE>
  <EM_APRM_MODIF_PAYM_SCHED><![CDATA[N]]></EM_APRM_MODIF_PAYM_SCHED>
  <EM_APRM_MODIF_PAYM_OUT_SCHED><![CDATA[N]]></EM_APRM_MODIF_PAYM_OUT_SCHED>
</FIN_PAYMENT_SCHEDULE>

<FIN_PAYMENT_SCHEDULE>
  <FIN_PAYMENT_SCHEDULE_ID><![CDATA[84D38C05090C4025A832D5CA8F01AC87]]></FIN_PAYMENT_SCHEDULE_ID>
  <AD_CLIENT_ID><![CDATA[39363B0921BB4293B48383844325E84C]]></AD_CLIENT_ID>
  <AD_ORG_ID><![CDATA[BF129721D9FB4EB0819509934153E972]]></AD_ORG_ID>
  <CREATED><![CDATA[2013-07-04 23:01:16.744]]></CREATED>
  <CREATEDBY><![CDATA[0]]></CREATEDBY>
  <UPDATED><![CDATA[2013-07-04 23:01:16.744]]></UPDATED>
  <UPDATEDBY><![CDATA[0]]></UPDATEDBY>
  <C_INVOICE_ID><![CDATA[6636FC380B7144E9BDEE70B931DEB110]]></C_INVOICE_ID>
  <DUEDATE><![CDATA[2012-10-22 00:00:00.0]]></DUEDATE>
  <FIN_PAYMENTMETHOD_ID><![CDATA[5A741F883A31408CA3AC097D76AA6D32]]></FIN_PAYMENTMETHOD_ID>
  <C_CURRENCY_ID><![CDATA[102]]></C_CURRENCY_ID>
  <AMOUNT><![CDATA[1389370.40]]></AMOUNT>
  <PAIDAMT><![CDATA[0]]></PAIDAMT>
  <OUTSTANDINGAMT><![CDATA[1389370.40]]></OUTSTANDINGAMT>
  <ISACTIVE><![CDATA[Y]]></ISACTIVE>
  <UPDATE_PAYMENT_PLAN><![CDATA[Y]]></UPDATE_PAYMENT_PLAN>
  <EXPECTEDDATE><![CDATA[2012-10-22 00:00:00.0]]></EXPECTEDDATE>
  <EM_APRM_MODIF_PAYM_SCHED><![CDATA[N]]></EM_APRM_MODIF_PAYM_SCHED>
  <EM_APRM_MODIF_PAYM_OUT_SCHED><![CDATA[N]]></EM_APRM_MODIF_PAYM_OUT_SCHED>
</FIN_PAYMENT_SCHEDULE>

<FIN_PAYMENT_SCHEDULE>
  <FIN_PAYMENT_SCHEDULE_ID><![CDATA[86F878D3E81643C1A053BD0106B2F606]]></FIN_PAYMENT_SCHEDULE_ID>
  <AD_CLIENT_ID><![CDATA[39363B0921BB4293B48383844325E84C]]></AD_CLIENT_ID>
  <AD_ORG_ID><![CDATA[D270A5AC50874F8BA67A88EE977F8E3B]]></AD_ORG_ID>
  <CREATED><![CDATA[2013-07-04 23:01:16.7]]></CREATED>
  <CREATEDBY><![CDATA[0]]></CREATEDBY>
  <UPDATED><![CDATA[2013-07-04 23:01:16.7]]></UPDATED>
  <UPDATEDBY><![CDATA[0]]></UPDATEDBY>
  <C_INVOICE_ID><![CDATA[9EAD3F1B58D54B7C9BC00CFE4C083580]]></C_INVOICE_ID>
  <DUEDATE><![CDATA[2013-03-01 00:00:00.0]]></DUEDATE>
  <FIN_PAYMENTMETHOD_ID><![CDATA[45A202BF44884F05B8A1BF741E2063B6]]></FIN_PAYMENTMETHOD_ID>
  <C_CURRENCY_ID><![CDATA[102]]></C_CURRENCY_ID>
  <AMOUNT><![CDATA[174.80]]></AMOUNT>
  <PAIDAMT><![CDATA[174.80]]></PAIDAMT>
  <OUTSTANDINGAMT><![CDATA[0]]></OUTSTANDINGAMT>
  <ISACTIVE><![CDATA[Y]]></ISACTIVE>
  <UPDATE_PAYMENT_PLAN><![CDATA[Y]]></UPDATE_PAYMENT_PLAN>
  <EXPECTEDDATE><![CDATA[2013-03-01 00:00:00.0]]></EXPECTEDDATE>
  <EM_APRM_MODIF_PAYM_SCHED><![CDATA[N]]></EM_APRM_MODIF_PAYM_SCHED>
  <EM_APRM_MODIF_PAYM_OUT_SCHED><![CDATA[N]]></EM_APRM_MODIF_PAYM_OUT_SCHED>
</FIN_PAYMENT_SCHEDULE>

<FIN_PAYMENT_SCHEDULE>
  <FIN_PAYMENT_SCHEDULE_ID><![CDATA[9022E748D4034764AF6316EE85B8E218]]></FIN_PAYMENT_SCHEDULE_ID>
  <AD_CLIENT_ID><![CDATA[39363B0921BB4293B48383844325E84C]]></AD_CLIENT_ID>
  <AD_ORG_ID><![CDATA[3B187EC130A549A7A9388F8060EF156D]]></AD_ORG_ID>
  <CREATED><![CDATA[2014-04-22 13:02:12.002]]></CREATED>
  <CREATEDBY><![CDATA[1D0E5A14E65D474FA8EC8311E009E253]]></CREATEDBY>
  <UPDATED><![CDATA[2014-04-22 13:02:12.259]]></UPDATED>
  <UPDATEDBY><![CDATA[1D0E5A14E65D474FA8EC8311E009E253]]></UPDATEDBY>
  <C_INVOICE_ID><![CDATA[8C02DF6AEA0A479E9B3FC2CC33F51AE8]]></C_INVOICE_ID>
  <DUEDATE><![CDATA[2014-04-19 20:38:34.0]]></DUEDATE>
  <FIN_PAYMENTMETHOD_ID><![CDATA[45A202BF44884F05B8A1BF741E2063B6]]></FIN_PAYMENTMETHOD_ID>
  <C_CURRENCY_ID><![CDATA[102]]></C_CURRENCY_ID>
  <AMOUNT><![CDATA[54.50]]></AMOUNT>
  <PAIDAMT><![CDATA[54.50]]></PAIDAMT>
  <OUTSTANDINGAMT><![CDATA[0]]></OUTSTANDINGAMT>
  <ISACTIVE><![CDATA[Y]]></ISACTIVE>
  <UPDATE_PAYMENT_PLAN><![CDATA[Y]]></UPDATE_PAYMENT_PLAN>
  <EXPECTEDDATE><![CDATA[2014-04-19 20:38:34.0]]></EXPECTEDDATE>
  <EM_APRM_MODIF_PAYM_SCHED><![CDATA[N]]></EM_APRM_MODIF_PAYM_SCHED>
  <EM_APRM_MODIF_PAYM_OUT_SCHED><![CDATA[N]]></EM_APRM_MODIF_PAYM_OUT_SCHED>
</FIN_PAYMENT_SCHEDULE>

<FIN_PAYMENT_SCHEDULE>
  <FIN_PAYMENT_SCHEDULE_ID><![CDATA[972797770D124C98B71B62266B1B3B5F]]></FIN_PAYMENT_SCHEDULE_ID>
  <AD_CLIENT_ID><![CDATA[39363B0921BB4293B48383844325E84C]]></AD_CLIENT_ID>
  <AD_ORG_ID><![CDATA[BF129721D9FB4EB0819509934153E972]]></AD_ORG_ID>
  <CREATED><![CDATA[2013-07-04 23:01:16.744]]></CREATED>
  <CREATEDBY><![CDATA[0]]></CREATEDBY>
  <UPDATED><![CDATA[2013-07-04 23:01:16.744]]></UPDATED>
  <UPDATEDBY><![CDATA[0]]></UPDATEDBY>
  <C_ORDER_ID><![CDATA[C78EB6B8FF624CE8A301D3C76110DD48]]></C_ORDER_ID>
  <DUEDATE><![CDATA[2012-07-24 00:00:00.0]]></DUEDATE>
  <FIN_PAYMENTMETHOD_ID><![CDATA[5A741F883A31408CA3AC097D76AA6D32]]></FIN_PAYMENTMETHOD_ID>
  <C_CURRENCY_ID><![CDATA[102]]></C_CURRENCY_ID>
  <AMOUNT><![CDATA[157.0]]></AMOUNT>
  <PAIDAMT><![CDATA[0]]></PAIDAMT>
  <OUTSTANDINGAMT><![CDATA[157.0]]></OUTSTANDINGAMT>
  <ISACTIVE><![CDATA[Y]]></ISACTIVE>
  <UPDATE_PAYMENT_PLAN><![CDATA[Y]]></UPDATE_PAYMENT_PLAN>
  <EXPECTEDDATE><![CDATA[2012-07-24 00:00:00.0]]></EXPECTEDDATE>
  <EM_APRM_MODIF_PAYM_SCHED><![CDATA[N]]></EM_APRM_MODIF_PAYM_SCHED>
  <EM_APRM_MODIF_PAYM_OUT_SCHED><![CDATA[N]]></EM_APRM_MODIF_PAYM_OUT_SCHED>
</FIN_PAYMENT_SCHEDULE>

<FIN_PAYMENT_SCHEDULE>
  <FIN_PAYMENT_SCHEDULE_ID><![CDATA[9CDC5DDCE96E458AA958DB5105FC459C]]></FIN_PAYMENT_SCHEDULE_ID>
  <AD_CLIENT_ID><![CDATA[39363B0921BB4293B48383844325E84C]]></AD_CLIENT_ID>
  <AD_ORG_ID><![CDATA[D270A5AC50874F8BA67A88EE977F8E3B]]></AD_ORG_ID>
  <CREATED><![CDATA[2013-07-04 23:01:16.744]]></CREATED>
  <CREATEDBY><![CDATA[0]]></CREATEDBY>
  <UPDATED><![CDATA[2013-07-04 23:01:16.744]]></UPDATED>
  <UPDATEDBY><![CDATA[0]]></UPDATEDBY>
  <C_ORDER_ID><![CDATA[C7F46321C647C27B5CE85E74C430DCD5]]></C_ORDER_ID>
  <DUEDATE><![CDATA[2013-03-01 00:00:00.0]]></DUEDATE>
  <FIN_PAYMENTMETHOD_ID><![CDATA[45A202BF44884F05B8A1BF741E2063B6]]></FIN_PAYMENTMETHOD_ID>
  <C_CURRENCY_ID><![CDATA[102]]></C_CURRENCY_ID>
  <AMOUNT><![CDATA[1104.80]]></AMOUNT>
  <PAIDAMT><![CDATA[300.00]]></PAIDAMT>
  <OUTSTANDINGAMT><![CDATA[804.80]]></OUTSTANDINGAMT>
  <ISACTIVE><![CDATA[Y]]></ISACTIVE>
  <UPDATE_PAYMENT_PLAN><![CDATA[Y]]></UPDATE_PAYMENT_PLAN>
  <EXPECTEDDATE><![CDATA[2013-03-01 00:00:00.0]]></EXPECTEDDATE>
  <EM_APRM_MODIF_PAYM_SCHED><![CDATA[N]]></EM_APRM_MODIF_PAYM_SCHED>
  <EM_APRM_MODIF_PAYM_OUT_SCHED><![CDATA[N]]></EM_APRM_MODIF_PAYM_OUT_SCHED>
</FIN_PAYMENT_SCHEDULE>

<FIN_PAYMENT_SCHEDULE>
  <FIN_PAYMENT_SCHEDULE_ID><![CDATA[9D8CE7E279064741B1D9D06041200349]]></FIN_PAYMENT_SCHEDULE_ID>
  <AD_CLIENT_ID><![CDATA[39363B0921BB4293B48383844325E84C]]></AD_CLIENT_ID>
  <AD_ORG_ID><![CDATA[D270A5AC50874F8BA67A88EE977F8E3B]]></AD_ORG_ID>
  <CREATED><![CDATA[2014-04-19 20:35:13.919]]></CREATED>
  <CREATEDBY><![CDATA[3073EDF96A3C42CC86C7069E379522D2]]></CREATEDBY>
  <UPDATED><![CDATA[2014-04-19 20:35:14.105]]></UPDATED>
  <UPDATEDBY><![CDATA[3073EDF96A3C42CC86C7069E379522D2]]></UPDATEDBY>
  <C_ORDER_ID><![CDATA[A6DC59B417BAAC7D0CFA70D20130E2A5]]></C_ORDER_ID>
  <DUEDATE><![CDATA[2014-04-19 00:00:00.0]]></DUEDATE>
  <FIN_PAYMENTMETHOD_ID><![CDATA[45A202BF44884F05B8A1BF741E2063B6]]></FIN_PAYMENTMETHOD_ID>
  <C_CURRENCY_ID><![CDATA[102]]></C_CURRENCY_ID>
  <AMOUNT><![CDATA[54.50]]></AMOUNT>
  <PAIDAMT><![CDATA[54.50]]></PAIDAMT>
  <OUTSTANDINGAMT><![CDATA[0.00]]></OUTSTANDINGAMT>
  <ISACTIVE><![CDATA[Y]]></ISACTIVE>
  <UPDATE_PAYMENT_PLAN><![CDATA[Y]]></UPDATE_PAYMENT_PLAN>
  <EXPECTEDDATE><![CDATA[2014-04-19 00:00:00.0]]></EXPECTEDDATE>
  <EM_APRM_MODIF_PAYM_SCHED><![CDATA[N]]></EM_APRM_MODIF_PAYM_SCHED>
  <EM_APRM_MODIF_PAYM_OUT_SCHED><![CDATA[N]]></EM_APRM_MODIF_PAYM_OUT_SCHED>
</FIN_PAYMENT_SCHEDULE>

<FIN_PAYMENT_SCHEDULE>
  <FIN_PAYMENT_SCHEDULE_ID><![CDATA[A008C2ED79714C90A2ADBC2C5C3ACC86]]></FIN_PAYMENT_SCHEDULE_ID>
  <AD_CLIENT_ID><![CDATA[39363B0921BB4293B48383844325E84C]]></AD_CLIENT_ID>
  <AD_ORG_ID><![CDATA[3B187EC130A549A7A9388F8060EF156D]]></AD_ORG_ID>
  <CREATED><![CDATA[2013-07-04 23:01:16.702]]></CREATED>
  <CREATEDBY><![CDATA[0]]></CREATEDBY>
  <UPDATED><![CDATA[2013-07-04 23:01:16.702]]></UPDATED>
  <UPDATEDBY><![CDATA[0]]></UPDATEDBY>
  <C_ORDER_ID><![CDATA[8965162E92054817A4691390877C0195]]></C_ORDER_ID>
  <DUEDATE><![CDATA[2012-07-24 00:00:00.0]]></DUEDATE>
  <FIN_PAYMENTMETHOD_ID><![CDATA[45A202BF44884F05B8A1BF741E2063B6]]></FIN_PAYMENTMETHOD_ID>
  <C_CURRENCY_ID><![CDATA[102]]></C_CURRENCY_ID>
  <AMOUNT><![CDATA[89.8]]></AMOUNT>
  <PAIDAMT><![CDATA[89.8]]></PAIDAMT>
  <OUTSTANDINGAMT><![CDATA[0.0]]></OUTSTANDINGAMT>
  <ISACTIVE><![CDATA[Y]]></ISACTIVE>
  <UPDATE_PAYMENT_PLAN><![CDATA[Y]]></UPDATE_PAYMENT_PLAN>
  <EXPECTEDDATE><![CDATA[2012-07-24 00:00:00.0]]></EXPECTEDDATE>
  <EM_APRM_MODIF_PAYM_SCHED><![CDATA[N]]></EM_APRM_MODIF_PAYM_SCHED>
  <EM_APRM_MODIF_PAYM_OUT_SCHED><![CDATA[N]]></EM_APRM_MODIF_PAYM_OUT_SCHED>
</FIN_PAYMENT_SCHEDULE>

<FIN_PAYMENT_SCHEDULE>
  <FIN_PAYMENT_SCHEDULE_ID><![CDATA[A169710FDBBF40278D483F244301B084]]></FIN_PAYMENT_SCHEDULE_ID>
  <AD_CLIENT_ID><![CDATA[39363B0921BB4293B48383844325E84C]]></AD_CLIENT_ID>
  <AD_ORG_ID><![CDATA[3B187EC130A549A7A9388F8060EF156D]]></AD_ORG_ID>
  <CREATED><![CDATA[2013-07-04 23:01:16.7]]></CREATED>
  <CREATEDBY><![CDATA[0]]></CREATEDBY>
  <UPDATED><![CDATA[2013-07-04 23:01:16.7]]></UPDATED>
  <UPDATEDBY><![CDATA[0]]></UPDATEDBY>
  <C_ORDER_ID><![CDATA[3F1174065F2545348AEA69B559B2DA96]]></C_ORDER_ID>
  <DUEDATE><![CDATA[2012-07-24 00:00:00.0]]></DUEDATE>
  <FIN_PAYMENTMETHOD_ID><![CDATA[45A202BF44884F05B8A1BF741E2063B6]]></FIN_PAYMENTMETHOD_ID>
  <C_CURRENCY_ID><![CDATA[102]]></C_CURRENCY_ID>
  <AMOUNT><![CDATA[126.0]]></AMOUNT>
  <PAIDAMT><![CDATA[126.0]]></PAIDAMT>
  <OUTSTANDINGAMT><![CDATA[0.0]]></OUTSTANDINGAMT>
  <ISACTIVE><![CDATA[Y]]></ISACTIVE>
  <UPDATE_PAYMENT_PLAN><![CDATA[Y]]></UPDATE_PAYMENT_PLAN>
  <EXPECTEDDATE><![CDATA[2012-07-24 00:00:00.0]]></EXPECTEDDATE>
  <EM_APRM_MODIF_PAYM_SCHED><![CDATA[N]]></EM_APRM_MODIF_PAYM_SCHED>
  <EM_APRM_MODIF_PAYM_OUT_SCHED><![CDATA[N]]></EM_APRM_MODIF_PAYM_OUT_SCHED>
</FIN_PAYMENT_SCHEDULE>

<FIN_PAYMENT_SCHEDULE>
  <FIN_PAYMENT_SCHEDULE_ID><![CDATA[A49D4F4614FD4115BFC05187CEDC125D]]></FIN_PAYMENT_SCHEDULE_ID>
  <AD_CLIENT_ID><![CDATA[39363B0921BB4293B48383844325E84C]]></AD_CLIENT_ID>
  <AD_ORG_ID><![CDATA[D270A5AC50874F8BA67A88EE977F8E3B]]></AD_ORG_ID>
  <CREATED><![CDATA[2013-07-04 23:01:16.701]]></CREATED>
  <CREATEDBY><![CDATA[0]]></CREATEDBY>
  <UPDATED><![CDATA[2013-07-04 23:01:16.701]]></UPDATED>
  <UPDATEDBY><![CDATA[0]]></UPDATEDBY>
  <C_ORDER_ID><![CDATA[5A3E9F9A33514A8D87209AFAFA9A43E6]]></C_ORDER_ID>
  <DUEDATE><![CDATA[2012-07-24 00:00:00.0]]></DUEDATE>
  <FIN_PAYMENTMETHOD_ID><![CDATA[45A202BF44884F05B8A1BF741E2063B6]]></FIN_PAYMENTMETHOD_ID>
  <C_CURRENCY_ID><![CDATA[102]]></C_CURRENCY_ID>
  <AMOUNT><![CDATA[89.5]]></AMOUNT>
  <PAIDAMT><![CDATA[89.5]]></PAIDAMT>
  <OUTSTANDINGAMT><![CDATA[0.0]]></OUTSTANDINGAMT>
  <ISACTIVE><![CDATA[Y]]></ISACTIVE>
  <UPDATE_PAYMENT_PLAN><![CDATA[Y]]></UPDATE_PAYMENT_PLAN>
  <EXPECTEDDATE><![CDATA[2012-07-24 00:00:00.0]]></EXPECTEDDATE>
  <EM_APRM_MODIF_PAYM_SCHED><![CDATA[N]]></EM_APRM_MODIF_PAYM_SCHED>
  <EM_APRM_MODIF_PAYM_OUT_SCHED><![CDATA[N]]></EM_APRM_MODIF_PAYM_OUT_SCHED>
</FIN_PAYMENT_SCHEDULE>

<FIN_PAYMENT_SCHEDULE>
  <FIN_PAYMENT_SCHEDULE_ID><![CDATA[A804B1209BC744838D4792FE4E9364C7]]></FIN_PAYMENT_SCHEDULE_ID>
  <AD_CLIENT_ID><![CDATA[39363B0921BB4293B48383844325E84C]]></AD_CLIENT_ID>
  <AD_ORG_ID><![CDATA[D270A5AC50874F8BA67A88EE977F8E3B]]></AD_ORG_ID>
  <CREATED><![CDATA[2013-07-04 23:01:16.744]]></CREATED>
  <CREATEDBY><![CDATA[0]]></CREATEDBY>
  <UPDATED><![CDATA[2013-07-04 23:01:16.744]]></UPDATED>
  <UPDATEDBY><![CDATA[0]]></UPDATEDBY>
  <C_ORDER_ID><![CDATA[43FF362780C4DF3CC7802AAFE1453B4A]]></C_ORDER_ID>
  <DUEDATE><![CDATA[2013-03-01 00:00:00.0]]></DUEDATE>
  <FIN_PAYMENTMETHOD_ID><![CDATA[45A202BF44884F05B8A1BF741E2063B6]]></FIN_PAYMENTMETHOD_ID>
  <C_CURRENCY_ID><![CDATA[102]]></C_CURRENCY_ID>
  <AMOUNT><![CDATA[379.30]]></AMOUNT>
  <PAIDAMT><![CDATA[0]]></PAIDAMT>
  <OUTSTANDINGAMT><![CDATA[379.30]]></OUTSTANDINGAMT>
  <ISACTIVE><![CDATA[Y]]></ISACTIVE>
  <UPDATE_PAYMENT_PLAN><![CDATA[Y]]></UPDATE_PAYMENT_PLAN>
  <EXPECTEDDATE><![CDATA[2013-03-01 00:00:00.0]]></EXPECTEDDATE>
  <EM_APRM_MODIF_PAYM_SCHED><![CDATA[N]]></EM_APRM_MODIF_PAYM_SCHED>
  <EM_APRM_MODIF_PAYM_OUT_SCHED><![CDATA[N]]></EM_APRM_MODIF_PAYM_OUT_SCHED>
</FIN_PAYMENT_SCHEDULE>

<FIN_PAYMENT_SCHEDULE>
  <FIN_PAYMENT_SCHEDULE_ID><![CDATA[AA2DAC7A25314F1898C130BF8CC940EE]]></FIN_PAYMENT_SCHEDULE_ID>
  <AD_CLIENT_ID><![CDATA[39363B0921BB4293B48383844325E84C]]></AD_CLIENT_ID>
  <AD_ORG_ID><![CDATA[67839EEFA49E44AC969BD60093FCC899]]></AD_ORG_ID>
  <CREATED><![CDATA[2013-07-04 23:01:16.744]]></CREATED>
  <CREATEDBY><![CDATA[0]]></CREATEDBY>
  <UPDATED><![CDATA[2013-07-04 23:01:16.744]]></UPDATED>
  <UPDATEDBY><![CDATA[0]]></UPDATEDBY>
  <C_ORDER_ID><![CDATA[1F2E986EFED241A59649237BD7FC0F04]]></C_ORDER_ID>
  <DUEDATE><![CDATA[2012-07-24 00:00:00.0]]></DUEDATE>
  <FIN_PAYMENTMETHOD_ID><![CDATA[45A202BF44884F05B8A1BF741E2063B6]]></FIN_PAYMENTMETHOD_ID>
  <C_CURRENCY_ID><![CDATA[102]]></C_CURRENCY_ID>
  <AMOUNT><![CDATA[1186.1]]></AMOUNT>
  <PAIDAMT><![CDATA[1186.1]]></PAIDAMT>
  <OUTSTANDINGAMT><![CDATA[0.0]]></OUTSTANDINGAMT>
  <ISACTIVE><![CDATA[Y]]></ISACTIVE>
  <UPDATE_PAYMENT_PLAN><![CDATA[Y]]></UPDATE_PAYMENT_PLAN>
  <EXPECTEDDATE><![CDATA[2012-07-24 00:00:00.0]]></EXPECTEDDATE>
  <EM_APRM_MODIF_PAYM_SCHED><![CDATA[N]]></EM_APRM_MODIF_PAYM_SCHED>
  <EM_APRM_MODIF_PAYM_OUT_SCHED><![CDATA[N]]></EM_APRM_MODIF_PAYM_OUT_SCHED>
</FIN_PAYMENT_SCHEDULE>

<FIN_PAYMENT_SCHEDULE>
  <FIN_PAYMENT_SCHEDULE_ID><![CDATA[AA8FDF84E47746E08541C287971C86B9]]></FIN_PAYMENT_SCHEDULE_ID>
  <AD_CLIENT_ID><![CDATA[39363B0921BB4293B48383844325E84C]]></AD_CLIENT_ID>
  <AD_ORG_ID><![CDATA[B5DE96143D6642228E3B9DEC69886A47]]></AD_ORG_ID>
  <CREATED><![CDATA[2013-07-04 23:01:16.701]]></CREATED>
  <CREATEDBY><![CDATA[0]]></CREATEDBY>
  <UPDATED><![CDATA[2013-07-04 23:01:16.701]]></UPDATED>
  <UPDATEDBY><![CDATA[0]]></UPDATEDBY>
  <C_ORDER_ID><![CDATA[0A92C1CC466F4274BD158B356222B52A]]></C_ORDER_ID>
  <DUEDATE><![CDATA[2012-07-24 00:00:00.0]]></DUEDATE>
  <FIN_PAYMENTMETHOD_ID><![CDATA[45A202BF44884F05B8A1BF741E2063B6]]></FIN_PAYMENTMETHOD_ID>
  <C_CURRENCY_ID><![CDATA[102]]></C_CURRENCY_ID>
  <AMOUNT><![CDATA[82.08]]></AMOUNT>
  <PAIDAMT><![CDATA[82.08]]></PAIDAMT>
  <OUTSTANDINGAMT><![CDATA[0.00]]></OUTSTANDINGAMT>
  <ISACTIVE><![CDATA[Y]]></ISACTIVE>
  <UPDATE_PAYMENT_PLAN><![CDATA[Y]]></UPDATE_PAYMENT_PLAN>
  <EXPECTEDDATE><![CDATA[2012-07-24 00:00:00.0]]></EXPECTEDDATE>
  <EM_APRM_MODIF_PAYM_SCHED><![CDATA[N]]></EM_APRM_MODIF_PAYM_SCHED>
  <EM_APRM_MODIF_PAYM_OUT_SCHED><![CDATA[N]]></EM_APRM_MODIF_PAYM_OUT_SCHED>
</FIN_PAYMENT_SCHEDULE>

<FIN_PAYMENT_SCHEDULE>
  <FIN_PAYMENT_SCHEDULE_ID><![CDATA[AB0DB29C0796429CA763B83340981E6C]]></FIN_PAYMENT_SCHEDULE_ID>
  <AD_CLIENT_ID><![CDATA[39363B0921BB4293B48383844325E84C]]></AD_CLIENT_ID>
  <AD_ORG_ID><![CDATA[B5DE96143D6642228E3B9DEC69886A47]]></AD_ORG_ID>
  <CREATED><![CDATA[2013-07-04 23:01:16.7]]></CREATED>
  <CREATEDBY><![CDATA[0]]></CREATEDBY>
  <UPDATED><![CDATA[2013-07-04 23:01:16.7]]></UPDATED>
  <UPDATEDBY><![CDATA[0]]></UPDATEDBY>
  <C_ORDER_ID><![CDATA[B6E14AC1552B4F8FA03B74851DAAE71C]]></C_ORDER_ID>
  <DUEDATE><![CDATA[2012-07-24 00:00:00.0]]></DUEDATE>
  <FIN_PAYMENTMETHOD_ID><![CDATA[45A202BF44884F05B8A1BF741E2063B6]]></FIN_PAYMENTMETHOD_ID>
  <C_CURRENCY_ID><![CDATA[102]]></C_CURRENCY_ID>
  <AMOUNT><![CDATA[95.52]]></AMOUNT>
  <PAIDAMT><![CDATA[95.52]]></PAIDAMT>
  <OUTSTANDINGAMT><![CDATA[0.00]]></OUTSTANDINGAMT>
  <ISACTIVE><![CDATA[Y]]></ISACTIVE>
  <UPDATE_PAYMENT_PLAN><![CDATA[Y]]></UPDATE_PAYMENT_PLAN>
  <EXPECTEDDATE><![CDATA[2012-07-24 00:00:00.0]]></EXPECTEDDATE>
  <EM_APRM_MODIF_PAYM_SCHED><![CDATA[N]]></EM_APRM_MODIF_PAYM_SCHED>
  <EM_APRM_MODIF_PAYM_OUT_SCHED><![CDATA[N]]></EM_APRM_MODIF_PAYM_OUT_SCHED>
</FIN_PAYMENT_SCHEDULE>

<FIN_PAYMENT_SCHEDULE>
  <FIN_PAYMENT_SCHEDULE_ID><![CDATA[AD7E372E44634D018795EA80EA9DD00E]]></FIN_PAYMENT_SCHEDULE_ID>
  <AD_CLIENT_ID><![CDATA[39363B0921BB4293B48383844325E84C]]></AD_CLIENT_ID>
  <AD_ORG_ID><![CDATA[3B187EC130A549A7A9388F8060EF156D]]></AD_ORG_ID>
  <CREATED><![CDATA[2013-07-04 23:01:16.701]]></CREATED>
  <CREATEDBY><![CDATA[0]]></CREATEDBY>
  <UPDATED><![CDATA[2013-07-04 23:01:16.701]]></UPDATED>
  <UPDATEDBY><![CDATA[0]]></UPDATEDBY>
  <C_ORDER_ID><![CDATA[4CF23FC08F4E49468E69106A8A056022]]></C_ORDER_ID>
  <DUEDATE><![CDATA[2012-07-24 00:00:00.0]]></DUEDATE>
  <FIN_PAYMENTMETHOD_ID><![CDATA[45A202BF44884F05B8A1BF741E2063B6]]></FIN_PAYMENTMETHOD_ID>
  <C_CURRENCY_ID><![CDATA[102]]></C_CURRENCY_ID>
  <AMOUNT><![CDATA[314.9]]></AMOUNT>
  <PAIDAMT><![CDATA[314.9]]></PAIDAMT>
  <OUTSTANDINGAMT><![CDATA[0.0]]></OUTSTANDINGAMT>
  <ISACTIVE><![CDATA[Y]]></ISACTIVE>
  <UPDATE_PAYMENT_PLAN><![CDATA[Y]]></UPDATE_PAYMENT_PLAN>
  <EXPECTEDDATE><![CDATA[2012-07-24 00:00:00.0]]></EXPECTEDDATE>
  <EM_APRM_MODIF_PAYM_SCHED><![CDATA[N]]></EM_APRM_MODIF_PAYM_SCHED>
  <EM_APRM_MODIF_PAYM_OUT_SCHED><![CDATA[N]]></EM_APRM_MODIF_PAYM_OUT_SCHED>
</FIN_PAYMENT_SCHEDULE>

<FIN_PAYMENT_SCHEDULE>
  <FIN_PAYMENT_SCHEDULE_ID><![CDATA[B67D1BED0CB3449CA03AB0735DA20665]]></FIN_PAYMENT_SCHEDULE_ID>
  <AD_CLIENT_ID><![CDATA[39363B0921BB4293B48383844325E84C]]></AD_CLIENT_ID>
  <AD_ORG_ID><![CDATA[B5DE96143D6642228E3B9DEC69886A47]]></AD_ORG_ID>
  <CREATED><![CDATA[2013-07-04 23:01:16.702]]></CREATED>
  <CREATEDBY><![CDATA[0]]></CREATEDBY>
  <UPDATED><![CDATA[2013-07-04 23:01:16.702]]></UPDATED>
  <UPDATEDBY><![CDATA[0]]></UPDATEDBY>
  <C_ORDER_ID><![CDATA[1F9CE03465334C599FC7FE30FA794DA5]]></C_ORDER_ID>
  <DUEDATE><![CDATA[2012-07-24 00:00:00.0]]></DUEDATE>
  <FIN_PAYMENTMETHOD_ID><![CDATA[45A202BF44884F05B8A1BF741E2063B6]]></FIN_PAYMENTMETHOD_ID>
  <C_CURRENCY_ID><![CDATA[102]]></C_CURRENCY_ID>
  <AMOUNT><![CDATA[220.72]]></AMOUNT>
  <PAIDAMT><![CDATA[220.72]]></PAIDAMT>
  <OUTSTANDINGAMT><![CDATA[0.00]]></OUTSTANDINGAMT>
  <ISACTIVE><![CDATA[Y]]></ISACTIVE>
  <UPDATE_PAYMENT_PLAN><![CDATA[Y]]></UPDATE_PAYMENT_PLAN>
  <EXPECTEDDATE><![CDATA[2012-07-24 00:00:00.0]]></EXPECTEDDATE>
  <EM_APRM_MODIF_PAYM_SCHED><![CDATA[N]]></EM_APRM_MODIF_PAYM_SCHED>
  <EM_APRM_MODIF_PAYM_OUT_SCHED><![CDATA[N]]></EM_APRM_MODIF_PAYM_OUT_SCHED>
</FIN_PAYMENT_SCHEDULE>

<FIN_PAYMENT_SCHEDULE>
  <FIN_PAYMENT_SCHEDULE_ID><![CDATA[B8D325E33CDE440B8F317D3BAA91B7BE]]></FIN_PAYMENT_SCHEDULE_ID>
  <AD_CLIENT_ID><![CDATA[39363B0921BB4293B48383844325E84C]]></AD_CLIENT_ID>
  <AD_ORG_ID><![CDATA[3B187EC130A549A7A9388F8060EF156D]]></AD_ORG_ID>
  <CREATED><![CDATA[2013-07-04 23:01:16.699]]></CREATED>
  <CREATEDBY><![CDATA[0]]></CREATEDBY>
  <UPDATED><![CDATA[2013-07-04 23:01:16.699]]></UPDATED>
  <UPDATEDBY><![CDATA[0]]></UPDATEDBY>
  <C_INVOICE_ID><![CDATA[DED6EAF9A55C4BB2A79D5602AC03BECA]]></C_INVOICE_ID>
  <DUEDATE><![CDATA[2012-07-24 12:45:20.743]]></DUEDATE>
  <FIN_PAYMENTMETHOD_ID><![CDATA[45A202BF44884F05B8A1BF741E2063B6]]></FIN_PAYMENTMETHOD_ID>
  <C_CURRENCY_ID><![CDATA[102]]></C_CURRENCY_ID>
  <AMOUNT><![CDATA[699.8]]></AMOUNT>
  <PAIDAMT><![CDATA[699.8]]></PAIDAMT>
  <OUTSTANDINGAMT><![CDATA[0]]></OUTSTANDINGAMT>
  <ISACTIVE><![CDATA[Y]]></ISACTIVE>
  <UPDATE_PAYMENT_PLAN><![CDATA[Y]]></UPDATE_PAYMENT_PLAN>
  <EXPECTEDDATE><![CDATA[2012-07-24 12:45:20.743]]></EXPECTEDDATE>
  <EM_APRM_MODIF_PAYM_SCHED><![CDATA[N]]></EM_APRM_MODIF_PAYM_SCHED>
  <EM_APRM_MODIF_PAYM_OUT_SCHED><![CDATA[N]]></EM_APRM_MODIF_PAYM_OUT_SCHED>
</FIN_PAYMENT_SCHEDULE>

<FIN_PAYMENT_SCHEDULE>
  <FIN_PAYMENT_SCHEDULE_ID><![CDATA[BB07D691EAC4468D9C8D9EBF4184A641]]></FIN_PAYMENT_SCHEDULE_ID>
  <AD_CLIENT_ID><![CDATA[39363B0921BB4293B48383844325E84C]]></AD_CLIENT_ID>
  <AD_ORG_ID><![CDATA[BF129721D9FB4EB0819509934153E972]]></AD_ORG_ID>
  <CREATED><![CDATA[2013-07-04 23:01:16.744]]></CREATED>
  <CREATEDBY><![CDATA[0]]></CREATEDBY>
  <UPDATED><![CDATA[2013-07-04 23:01:16.744]]></UPDATED>
  <UPDATEDBY><![CDATA[0]]></UPDATEDBY>
  <C_ORDER_ID><![CDATA[1FC52443A5AC4A088CC2BBA5BFDD108C]]></C_ORDER_ID>
  <DUEDATE><![CDATA[2012-07-21 00:00:00.0]]></DUEDATE>
  <FIN_PAYMENTMETHOD_ID><![CDATA[5A741F883A31408CA3AC097D76AA6D32]]></FIN_PAYMENTMETHOD_ID>
  <C_CURRENCY_ID><![CDATA[102]]></C_CURRENCY_ID>
  <AMOUNT><![CDATA[6546.05]]></AMOUNT>
  <PAIDAMT><![CDATA[0]]></PAIDAMT>
  <OUTSTANDINGAMT><![CDATA[6546.05]]></OUTSTANDINGAMT>
  <ISACTIVE><![CDATA[Y]]></ISACTIVE>
  <UPDATE_PAYMENT_PLAN><![CDATA[Y]]></UPDATE_PAYMENT_PLAN>
  <EXPECTEDDATE><![CDATA[2012-07-21 00:00:00.0]]></EXPECTEDDATE>
  <EM_APRM_MODIF_PAYM_SCHED><![CDATA[N]]></EM_APRM_MODIF_PAYM_SCHED>
  <EM_APRM_MODIF_PAYM_OUT_SCHED><![CDATA[N]]></EM_APRM_MODIF_PAYM_OUT_SCHED>
</FIN_PAYMENT_SCHEDULE>

<FIN_PAYMENT_SCHEDULE>
  <FIN_PAYMENT_SCHEDULE_ID><![CDATA[BCEE6C6F5BC148949BE071C2C9FADB94]]></FIN_PAYMENT_SCHEDULE_ID>
  <AD_CLIENT_ID><![CDATA[39363B0921BB4293B48383844325E84C]]></AD_CLIENT_ID>
  <AD_ORG_ID><![CDATA[B5DE96143D6642228E3B9DEC69886A47]]></AD_ORG_ID>
  <CREATED><![CDATA[2013-07-04 23:01:16.698]]></CREATED>
  <CREATEDBY><![CDATA[0]]></CREATEDBY>
  <UPDATED><![CDATA[2013-07-04 23:01:16.698]]></UPDATED>
  <UPDATEDBY><![CDATA[0]]></UPDATEDBY>
  <C_INVOICE_ID><![CDATA[78C414C6F09447CC9CE42CD4FCCBF71F]]></C_INVOICE_ID>
  <DUEDATE><![CDATA[2012-07-24 12:40:45.92]]></DUEDATE>
  <FIN_PAYMENTMETHOD_ID><![CDATA[45A202BF44884F05B8A1BF741E2063B6]]></FIN_PAYMENTMETHOD_ID>
  <C_CURRENCY_ID><![CDATA[102]]></C_CURRENCY_ID>
  <AMOUNT><![CDATA[606.96]]></AMOUNT>
  <PAIDAMT><![CDATA[606.96]]></PAIDAMT>
  <OUTSTANDINGAMT><![CDATA[0]]></OUTSTANDINGAMT>
  <ISACTIVE><![CDATA[Y]]></ISACTIVE>
  <UPDATE_PAYMENT_PLAN><![CDATA[Y]]></UPDATE_PAYMENT_PLAN>
  <EXPECTEDDATE><![CDATA[2012-07-24 12:40:45.92]]></EXPECTEDDATE>
  <EM_APRM_MODIF_PAYM_SCHED><![CDATA[N]]></EM_APRM_MODIF_PAYM_SCHED>
  <EM_APRM_MODIF_PAYM_OUT_SCHED><![CDATA[N]]></EM_APRM_MODIF_PAYM_OUT_SCHED>
</FIN_PAYMENT_SCHEDULE>

<FIN_PAYMENT_SCHEDULE>
  <FIN_PAYMENT_SCHEDULE_ID><![CDATA[BE8BF88E4AD34FFD8CEE591844B71470]]></FIN_PAYMENT_SCHEDULE_ID>
  <AD_CLIENT_ID><![CDATA[39363B0921BB4293B48383844325E84C]]></AD_CLIENT_ID>
  <AD_ORG_ID><![CDATA[B5DE96143D6642228E3B9DEC69886A47]]></AD_ORG_ID>
  <CREATED><![CDATA[2013-07-04 23:01:16.703]]></CREATED>
  <CREATEDBY><![CDATA[0]]></CREATEDBY>
  <UPDATED><![CDATA[2013-07-04 23:01:16.703]]></UPDATED>
  <UPDATEDBY><![CDATA[0]]></UPDATEDBY>
  <C_ORDER_ID><![CDATA[49F50324279B440893D3087305926020]]></C_ORDER_ID>
  <DUEDATE><![CDATA[2012-07-24 00:00:00.0]]></DUEDATE>
  <FIN_PAYMENTMETHOD_ID><![CDATA[45A202BF44884F05B8A1BF741E2063B6]]></FIN_PAYMENTMETHOD_ID>
  <C_CURRENCY_ID><![CDATA[102]]></C_CURRENCY_ID>
  <AMOUNT><![CDATA[92.4]]></AMOUNT>
  <PAIDAMT><![CDATA[92.4]]></PAIDAMT>
  <OUTSTANDINGAMT><![CDATA[0.0]]></OUTSTANDINGAMT>
  <ISACTIVE><![CDATA[Y]]></ISACTIVE>
  <UPDATE_PAYMENT_PLAN><![CDATA[Y]]></UPDATE_PAYMENT_PLAN>
  <EXPECTEDDATE><![CDATA[2012-07-24 00:00:00.0]]></EXPECTEDDATE>
  <EM_APRM_MODIF_PAYM_SCHED><![CDATA[N]]></EM_APRM_MODIF_PAYM_SCHED>
  <EM_APRM_MODIF_PAYM_OUT_SCHED><![CDATA[N]]></EM_APRM_MODIF_PAYM_OUT_SCHED>
</FIN_PAYMENT_SCHEDULE>

<FIN_PAYMENT_SCHEDULE>
  <FIN_PAYMENT_SCHEDULE_ID><![CDATA[C09EAC5DCE674D0DB1FADFDB2A27C292]]></FIN_PAYMENT_SCHEDULE_ID>
  <AD_CLIENT_ID><![CDATA[39363B0921BB4293B48383844325E84C]]></AD_CLIENT_ID>
  <AD_ORG_ID><![CDATA[D270A5AC50874F8BA67A88EE977F8E3B]]></AD_ORG_ID>
  <CREATED><![CDATA[2013-07-04 23:01:16.699]]></CREATED>
  <CREATEDBY><![CDATA[0]]></CREATEDBY>
  <UPDATED><![CDATA[2013-07-04 23:01:16.699]]></UPDATED>
  <UPDATEDBY><![CDATA[0]]></UPDATEDBY>
  <C_ORDER_ID><![CDATA[B97610E4593C45459A8502BDE9758D7A]]></C_ORDER_ID>
  <DUEDATE><![CDATA[2012-07-24 00:00:00.0]]></DUEDATE>
  <FIN_PAYMENTMETHOD_ID><![CDATA[45A202BF44884F05B8A1BF741E2063B6]]></FIN_PAYMENTMETHOD_ID>
  <C_CURRENCY_ID><![CDATA[102]]></C_CURRENCY_ID>
  <AMOUNT><![CDATA[221.0]]></AMOUNT>
  <PAIDAMT><![CDATA[221.0]]></PAIDAMT>
  <OUTSTANDINGAMT><![CDATA[0.0]]></OUTSTANDINGAMT>
  <ISACTIVE><![CDATA[Y]]></ISACTIVE>
  <UPDATE_PAYMENT_PLAN><![CDATA[Y]]></UPDATE_PAYMENT_PLAN>
  <EXPECTEDDATE><![CDATA[2012-07-24 00:00:00.0]]></EXPECTEDDATE>
  <EM_APRM_MODIF_PAYM_SCHED><![CDATA[N]]></EM_APRM_MODIF_PAYM_SCHED>
  <EM_APRM_MODIF_PAYM_OUT_SCHED><![CDATA[N]]></EM_APRM_MODIF_PAYM_OUT_SCHED>
</FIN_PAYMENT_SCHEDULE>

<FIN_PAYMENT_SCHEDULE>
  <FIN_PAYMENT_SCHEDULE_ID><![CDATA[C438E1A8BE2A4F3EA3C0FB52B14E999D]]></FIN_PAYMENT_SCHEDULE_ID>
  <AD_CLIENT_ID><![CDATA[39363B0921BB4293B48383844325E84C]]></AD_CLIENT_ID>
  <AD_ORG_ID><![CDATA[BF129721D9FB4EB0819509934153E972]]></AD_ORG_ID>
  <CREATED><![CDATA[2013-07-04 23:01:16.744]]></CREATED>
  <CREATEDBY><![CDATA[0]]></CREATEDBY>
  <UPDATED><![CDATA[2013-07-04 23:01:16.744]]></UPDATED>
  <UPDATEDBY><![CDATA[0]]></UPDATEDBY>
  <C_INVOICE_ID><![CDATA[23782FB6BC344E50B2F52EC90844DADD]]></C_INVOICE_ID>
  <DUEDATE><![CDATA[2012-10-22 00:00:00.0]]></DUEDATE>
  <FIN_PAYMENTMETHOD_ID><![CDATA[5A741F883A31408CA3AC097D76AA6D32]]></FIN_PAYMENTMETHOD_ID>
  <C_CURRENCY_ID><![CDATA[102]]></C_CURRENCY_ID>
  <AMOUNT><![CDATA[157.00]]></AMOUNT>
  <PAIDAMT><![CDATA[0]]></PAIDAMT>
  <OUTSTANDINGAMT><![CDATA[157.00]]></OUTSTANDINGAMT>
  <ISACTIVE><![CDATA[Y]]></ISACTIVE>
  <UPDATE_PAYMENT_PLAN><![CDATA[Y]]></UPDATE_PAYMENT_PLAN>
  <EXPECTEDDATE><![CDATA[2012-10-22 00:00:00.0]]></EXPECTEDDATE>
  <EM_APRM_MODIF_PAYM_SCHED><![CDATA[N]]></EM_APRM_MODIF_PAYM_SCHED>
  <EM_APRM_MODIF_PAYM_OUT_SCHED><![CDATA[N]]></EM_APRM_MODIF_PAYM_OUT_SCHED>
</FIN_PAYMENT_SCHEDULE>

<FIN_PAYMENT_SCHEDULE>
  <FIN_PAYMENT_SCHEDULE_ID><![CDATA[C6FAE8C5E27B4B2E8A99F6CB4CA3607E]]></FIN_PAYMENT_SCHEDULE_ID>
  <AD_CLIENT_ID><![CDATA[39363B0921BB4293B48383844325E84C]]></AD_CLIENT_ID>
  <AD_ORG_ID><![CDATA[B5DE96143D6642228E3B9DEC69886A47]]></AD_ORG_ID>
  <CREATED><![CDATA[2013-07-04 23:01:16.698]]></CREATED>
  <CREATEDBY><![CDATA[0]]></CREATEDBY>
  <UPDATED><![CDATA[2013-07-04 23:01:16.698]]></UPDATED>
  <UPDATEDBY><![CDATA[0]]></UPDATEDBY>
  <C_ORDER_ID><![CDATA[0C829896AA064967993903C5E7B5AA9F]]></C_ORDER_ID>
  <DUEDATE><![CDATA[2012-07-24 00:00:00.0]]></DUEDATE>
  <FIN_PAYMENTMETHOD_ID><![CDATA[45A202BF44884F05B8A1BF741E2063B6]]></FIN_PAYMENTMETHOD_ID>
  <C_CURRENCY_ID><![CDATA[102]]></C_CURRENCY_ID>
  <AMOUNT><![CDATA[116.24]]></AMOUNT>
  <PAIDAMT><![CDATA[116.24]]></PAIDAMT>
  <OUTSTANDINGAMT><![CDATA[0.00]]></OUTSTANDINGAMT>
  <ISACTIVE><![CDATA[Y]]></ISACTIVE>
  <UPDATE_PAYMENT_PLAN><![CDATA[Y]]></UPDATE_PAYMENT_PLAN>
  <EXPECTEDDATE><![CDATA[2012-07-24 00:00:00.0]]></EXPECTEDDATE>
  <EM_APRM_MODIF_PAYM_SCHED><![CDATA[N]]></EM_APRM_MODIF_PAYM_SCHED>
  <EM_APRM_MODIF_PAYM_OUT_SCHED><![CDATA[N]]></EM_APRM_MODIF_PAYM_OUT_SCHED>
</FIN_PAYMENT_SCHEDULE>

<FIN_PAYMENT_SCHEDULE>
  <FIN_PAYMENT_SCHEDULE_ID><![CDATA[CC23F34A922E4FB0882BC8BC99DB43BC]]></FIN_PAYMENT_SCHEDULE_ID>
  <AD_CLIENT_ID><![CDATA[39363B0921BB4293B48383844325E84C]]></AD_CLIENT_ID>
  <AD_ORG_ID><![CDATA[D270A5AC50874F8BA67A88EE977F8E3B]]></AD_ORG_ID>
  <CREATED><![CDATA[2014-04-22 13:10:39.259]]></CREATED>
  <CREATEDBY><![CDATA[3073EDF96A3C42CC86C7069E379522D2]]></CREATEDBY>
  <UPDATED><![CDATA[2014-04-22 13:10:39.698]]></UPDATED>
  <UPDATEDBY><![CDATA[3073EDF96A3C42CC86C7069E379522D2]]></UPDATEDBY>
  <C_ORDER_ID><![CDATA[D0BAAD7ACB6C384A12C2F934DDEE5EA9]]></C_ORDER_ID>
  <DUEDATE><![CDATA[2014-04-22 00:00:00.0]]></DUEDATE>
  <FIN_PAYMENTMETHOD_ID><![CDATA[45A202BF44884F05B8A1BF741E2063B6]]></FIN_PAYMENTMETHOD_ID>
  <C_CURRENCY_ID><![CDATA[102]]></C_CURRENCY_ID>
  <AMOUNT><![CDATA[3.60]]></AMOUNT>
  <PAIDAMT><![CDATA[3.60]]></PAIDAMT>
  <OUTSTANDINGAMT><![CDATA[0.00]]></OUTSTANDINGAMT>
  <ISACTIVE><![CDATA[Y]]></ISACTIVE>
  <UPDATE_PAYMENT_PLAN><![CDATA[Y]]></UPDATE_PAYMENT_PLAN>
  <EXPECTEDDATE><![CDATA[2014-04-22 00:00:00.0]]></EXPECTEDDATE>
  <EM_APRM_MODIF_PAYM_SCHED><![CDATA[N]]></EM_APRM_MODIF_PAYM_SCHED>
  <EM_APRM_MODIF_PAYM_OUT_SCHED><![CDATA[N]]></EM_APRM_MODIF_PAYM_OUT_SCHED>
</FIN_PAYMENT_SCHEDULE>

<FIN_PAYMENT_SCHEDULE>
  <FIN_PAYMENT_SCHEDULE_ID><![CDATA[CC4C8D0DD1D34D13B65B0132BE448E57]]></FIN_PAYMENT_SCHEDULE_ID>
  <AD_CLIENT_ID><![CDATA[39363B0921BB4293B48383844325E84C]]></AD_CLIENT_ID>
  <AD_ORG_ID><![CDATA[D270A5AC50874F8BA67A88EE977F8E3B]]></AD_ORG_ID>
  <CREATED><![CDATA[2013-07-04 23:01:16.703]]></CREATED>
  <CREATEDBY><![CDATA[0]]></CREATEDBY>
  <UPDATED><![CDATA[2013-07-04 23:01:16.703]]></UPDATED>
  <UPDATEDBY><![CDATA[0]]></UPDATEDBY>
  <C_ORDER_ID><![CDATA[32C94FB652904F3AB4835774631F685C]]></C_ORDER_ID>
  <DUEDATE><![CDATA[2012-07-24 00:00:00.0]]></DUEDATE>
  <FIN_PAYMENTMETHOD_ID><![CDATA[45A202BF44884F05B8A1BF741E2063B6]]></FIN_PAYMENTMETHOD_ID>
  <C_CURRENCY_ID><![CDATA[102]]></C_CURRENCY_ID>
  <AMOUNT><![CDATA[110.5]]></AMOUNT>
  <PAIDAMT><![CDATA[-110.5]]></PAIDAMT>
  <OUTSTANDINGAMT><![CDATA[221.0]]></OUTSTANDINGAMT>
  <ISACTIVE><![CDATA[Y]]></ISACTIVE>
  <UPDATE_PAYMENT_PLAN><![CDATA[Y]]></UPDATE_PAYMENT_PLAN>
  <EXPECTEDDATE><![CDATA[2012-07-24 00:00:00.0]]></EXPECTEDDATE>
  <EM_APRM_MODIF_PAYM_SCHED><![CDATA[N]]></EM_APRM_MODIF_PAYM_SCHED>
  <EM_APRM_MODIF_PAYM_OUT_SCHED><![CDATA[N]]></EM_APRM_MODIF_PAYM_OUT_SCHED>
</FIN_PAYMENT_SCHEDULE>

<FIN_PAYMENT_SCHEDULE>
  <FIN_PAYMENT_SCHEDULE_ID><![CDATA[CE41B00E6D2A4050A6197982DA9BF844]]></FIN_PAYMENT_SCHEDULE_ID>
  <AD_CLIENT_ID><![CDATA[39363B0921BB4293B48383844325E84C]]></AD_CLIENT_ID>
  <AD_ORG_ID><![CDATA[01AD882EFC8545ACA6455E2F6FD51EE9]]></AD_ORG_ID>
  <CREATED><![CDATA[2013-07-04 23:01:16.744]]></CREATED>
  <CREATEDBY><![CDATA[0]]></CREATEDBY>
  <UPDATED><![CDATA[2013-07-04 23:01:16.744]]></UPDATED>
  <UPDATEDBY><![CDATA[0]]></UPDATEDBY>
  <C_INVOICE_ID><![CDATA[60C5F618E8F0410FB9BD868D26F1A9D9]]></C_INVOICE_ID>
  <DUEDATE><![CDATA[2012-10-22 00:00:00.0]]></DUEDATE>
  <FIN_PAYMENTMETHOD_ID><![CDATA[5A741F883A31408CA3AC097D76AA6D32]]></FIN_PAYMENTMETHOD_ID>
  <C_CURRENCY_ID><![CDATA[102]]></C_CURRENCY_ID>
  <AMOUNT><![CDATA[1389370.40]]></AMOUNT>
  <PAIDAMT><![CDATA[0]]></PAIDAMT>
  <OUTSTANDINGAMT><![CDATA[1389370.40]]></OUTSTANDINGAMT>
  <ISACTIVE><![CDATA[Y]]></ISACTIVE>
  <UPDATE_PAYMENT_PLAN><![CDATA[Y]]></UPDATE_PAYMENT_PLAN>
  <EXPECTEDDATE><![CDATA[2012-10-22 00:00:00.0]]></EXPECTEDDATE>
  <EM_APRM_MODIF_PAYM_SCHED><![CDATA[N]]></EM_APRM_MODIF_PAYM_SCHED>
  <EM_APRM_MODIF_PAYM_OUT_SCHED><![CDATA[N]]></EM_APRM_MODIF_PAYM_OUT_SCHED>
</FIN_PAYMENT_SCHEDULE>

<FIN_PAYMENT_SCHEDULE>
  <FIN_PAYMENT_SCHEDULE_ID><![CDATA[D0FAFDDA31504C05889C083BF09304AA]]></FIN_PAYMENT_SCHEDULE_ID>
  <AD_CLIENT_ID><![CDATA[39363B0921BB4293B48383844325E84C]]></AD_CLIENT_ID>
  <AD_ORG_ID><![CDATA[3B187EC130A549A7A9388F8060EF156D]]></AD_ORG_ID>
  <CREATED><![CDATA[2014-04-19 20:33:59.0]]></CREATED>
  <CREATEDBY><![CDATA[100]]></CREATEDBY>
  <UPDATED><![CDATA[2014-04-19 20:33:59.0]]></UPDATED>
  <UPDATEDBY><![CDATA[100]]></UPDATEDBY>
  <C_ORDER_ID><![CDATA[174DFED912BE47A1BFDE9627890FE18B]]></C_ORDER_ID>
  <DUEDATE><![CDATA[2014-04-19 00:00:00.0]]></DUEDATE>
  <FIN_PAYMENTMETHOD_ID><![CDATA[5A741F883A31408CA3AC097D76AA6D32]]></FIN_PAYMENTMETHOD_ID>
  <C_CURRENCY_ID><![CDATA[102]]></C_CURRENCY_ID>
  <AMOUNT><![CDATA[76725.00]]></AMOUNT>
  <PAIDAMT><![CDATA[0]]></PAIDAMT>
  <OUTSTANDINGAMT><![CDATA[76725.00]]></OUTSTANDINGAMT>
  <ISACTIVE><![CDATA[Y]]></ISACTIVE>
  <UPDATE_PAYMENT_PLAN><![CDATA[Y]]></UPDATE_PAYMENT_PLAN>
  <EXPECTEDDATE><![CDATA[2014-04-19 00:00:00.0]]></EXPECTEDDATE>
  <EM_APRM_MODIF_PAYM_SCHED><![CDATA[N]]></EM_APRM_MODIF_PAYM_SCHED>
  <EM_APRM_MODIF_PAYM_OUT_SCHED><![CDATA[N]]></EM_APRM_MODIF_PAYM_OUT_SCHED>
</FIN_PAYMENT_SCHEDULE>

<FIN_PAYMENT_SCHEDULE>
  <FIN_PAYMENT_SCHEDULE_ID><![CDATA[D737A5268834409D84A0C5AD602DE55F]]></FIN_PAYMENT_SCHEDULE_ID>
  <AD_CLIENT_ID><![CDATA[39363B0921BB4293B48383844325E84C]]></AD_CLIENT_ID>
  <AD_ORG_ID><![CDATA[D270A5AC50874F8BA67A88EE977F8E3B]]></AD_ORG_ID>
  <CREATED><![CDATA[2013-07-04 23:01:16.744]]></CREATED>
  <CREATEDBY><![CDATA[0]]></CREATEDBY>
  <UPDATED><![CDATA[2013-07-04 23:01:16.744]]></UPDATED>
  <UPDATEDBY><![CDATA[0]]></UPDATEDBY>
  <C_ORDER_ID><![CDATA[7A7234D0FED19D621A45FBA9878BB503]]></C_ORDER_ID>
  <DUEDATE><![CDATA[2013-03-01 00:00:00.0]]></DUEDATE>
  <FIN_PAYMENTMETHOD_ID><![CDATA[45A202BF44884F05B8A1BF741E2063B6]]></FIN_PAYMENTMETHOD_ID>
  <C_CURRENCY_ID><![CDATA[102]]></C_CURRENCY_ID>
  <AMOUNT><![CDATA[1124.50]]></AMOUNT>
  <PAIDAMT><![CDATA[1124.50]]></PAIDAMT>
  <OUTSTANDINGAMT><![CDATA[0.00]]></OUTSTANDINGAMT>
  <ISACTIVE><![CDATA[Y]]></ISACTIVE>
  <UPDATE_PAYMENT_PLAN><![CDATA[Y]]></UPDATE_PAYMENT_PLAN>
  <EXPECTEDDATE><![CDATA[2013-03-01 00:00:00.0]]></EXPECTEDDATE>
  <EM_APRM_MODIF_PAYM_SCHED><![CDATA[N]]></EM_APRM_MODIF_PAYM_SCHED>
  <EM_APRM_MODIF_PAYM_OUT_SCHED><![CDATA[N]]></EM_APRM_MODIF_PAYM_OUT_SCHED>
</FIN_PAYMENT_SCHEDULE>

<FIN_PAYMENT_SCHEDULE>
  <FIN_PAYMENT_SCHEDULE_ID><![CDATA[D9AD19EA3856413988F37B8D7C044E03]]></FIN_PAYMENT_SCHEDULE_ID>
  <AD_CLIENT_ID><![CDATA[39363B0921BB4293B48383844325E84C]]></AD_CLIENT_ID>
  <AD_ORG_ID><![CDATA[D270A5AC50874F8BA67A88EE977F8E3B]]></AD_ORG_ID>
  <CREATED><![CDATA[2013-07-04 23:01:16.744]]></CREATED>
  <CREATEDBY><![CDATA[0]]></CREATEDBY>
  <UPDATED><![CDATA[2013-07-04 23:01:16.744]]></UPDATED>
  <UPDATEDBY><![CDATA[0]]></UPDATEDBY>
  <C_ORDER_ID><![CDATA[DD3231B4F337E08FFB9E4E429019E8C3]]></C_ORDER_ID>
  <DUEDATE><![CDATA[2013-03-01 00:00:00.0]]></DUEDATE>
  <FIN_PAYMENTMETHOD_ID><![CDATA[45A202BF44884F05B8A1BF741E2063B6]]></FIN_PAYMENTMETHOD_ID>
  <C_CURRENCY_ID><![CDATA[102]]></C_CURRENCY_ID>
  <AMOUNT><![CDATA[750.30]]></AMOUNT>
  <PAIDAMT><![CDATA[200.00]]></PAIDAMT>
  <OUTSTANDINGAMT><![CDATA[550.30]]></OUTSTANDINGAMT>
  <ISACTIVE><![CDATA[Y]]></ISACTIVE>
  <UPDATE_PAYMENT_PLAN><![CDATA[Y]]></UPDATE_PAYMENT_PLAN>
  <EXPECTEDDATE><![CDATA[2013-03-01 00:00:00.0]]></EXPECTEDDATE>
  <EM_APRM_MODIF_PAYM_SCHED><![CDATA[N]]></EM_APRM_MODIF_PAYM_SCHED>
  <EM_APRM_MODIF_PAYM_OUT_SCHED><![CDATA[N]]></EM_APRM_MODIF_PAYM_OUT_SCHED>
</FIN_PAYMENT_SCHEDULE>

<FIN_PAYMENT_SCHEDULE>
  <FIN_PAYMENT_SCHEDULE_ID><![CDATA[E2201D48FEF34C619FB115D065BA554F]]></FIN_PAYMENT_SCHEDULE_ID>
  <AD_CLIENT_ID><![CDATA[39363B0921BB4293B48383844325E84C]]></AD_CLIENT_ID>
  <AD_ORG_ID><![CDATA[D270A5AC50874F8BA67A88EE977F8E3B]]></AD_ORG_ID>
  <CREATED><![CDATA[2013-07-04 23:01:16.744]]></CREATED>
  <CREATEDBY><![CDATA[0]]></CREATEDBY>
  <UPDATED><![CDATA[2013-07-04 23:01:16.744]]></UPDATED>
  <UPDATEDBY><![CDATA[0]]></UPDATEDBY>
  <C_ORDER_ID><![CDATA[E5873F93F804A2F3B2B33220A4E36E3D]]></C_ORDER_ID>
  <DUEDATE><![CDATA[2013-03-01 00:00:00.0]]></DUEDATE>
  <FIN_PAYMENTMETHOD_ID><![CDATA[45A202BF44884F05B8A1BF741E2063B6]]></FIN_PAYMENTMETHOD_ID>
  <C_CURRENCY_ID><![CDATA[102]]></C_CURRENCY_ID>
  <AMOUNT><![CDATA[325.00]]></AMOUNT>
  <PAIDAMT><![CDATA[0]]></PAIDAMT>
  <OUTSTANDINGAMT><![CDATA[325.00]]></OUTSTANDINGAMT>
  <ISACTIVE><![CDATA[Y]]></ISACTIVE>
  <UPDATE_PAYMENT_PLAN><![CDATA[Y]]></UPDATE_PAYMENT_PLAN>
  <EXPECTEDDATE><![CDATA[2013-03-01 00:00:00.0]]></EXPECTEDDATE>
  <EM_APRM_MODIF_PAYM_SCHED><![CDATA[N]]></EM_APRM_MODIF_PAYM_SCHED>
  <EM_APRM_MODIF_PAYM_OUT_SCHED><![CDATA[N]]></EM_APRM_MODIF_PAYM_OUT_SCHED>
</FIN_PAYMENT_SCHEDULE>

<FIN_PAYMENT_SCHEDULE>
  <FIN_PAYMENT_SCHEDULE_ID><![CDATA[E39F63A3F870428E889D0E9B83CBA2C9]]></FIN_PAYMENT_SCHEDULE_ID>
  <AD_CLIENT_ID><![CDATA[39363B0921BB4293B48383844325E84C]]></AD_CLIENT_ID>
  <AD_ORG_ID><![CDATA[BF129721D9FB4EB0819509934153E972]]></AD_ORG_ID>
  <CREATED><![CDATA[2013-07-04 23:01:16.744]]></CREATED>
  <CREATEDBY><![CDATA[0]]></CREATEDBY>
  <UPDATED><![CDATA[2013-07-04 23:01:16.744]]></UPDATED>
  <UPDATEDBY><![CDATA[0]]></UPDATEDBY>
  <C_ORDER_ID><![CDATA[975B5D0AD40B44A2BF0DA988A7024F6F]]></C_ORDER_ID>
  <DUEDATE><![CDATA[2012-07-07 00:00:00.0]]></DUEDATE>
  <FIN_PAYMENTMETHOD_ID><![CDATA[5A741F883A31408CA3AC097D76AA6D32]]></FIN_PAYMENTMETHOD_ID>
  <C_CURRENCY_ID><![CDATA[102]]></C_CURRENCY_ID>
  <AMOUNT><![CDATA[1389370.40]]></AMOUNT>
  <PAIDAMT><![CDATA[0]]></PAIDAMT>
  <OUTSTANDINGAMT><![CDATA[1389370.40]]></OUTSTANDINGAMT>
  <ISACTIVE><![CDATA[Y]]></ISACTIVE>
  <UPDATE_PAYMENT_PLAN><![CDATA[Y]]></UPDATE_PAYMENT_PLAN>
  <EXPECTEDDATE><![CDATA[2012-07-07 00:00:00.0]]></EXPECTEDDATE>
  <EM_APRM_MODIF_PAYM_SCHED><![CDATA[N]]></EM_APRM_MODIF_PAYM_SCHED>
  <EM_APRM_MODIF_PAYM_OUT_SCHED><![CDATA[N]]></EM_APRM_MODIF_PAYM_OUT_SCHED>
</FIN_PAYMENT_SCHEDULE>

<FIN_PAYMENT_SCHEDULE>
  <FIN_PAYMENT_SCHEDULE_ID><![CDATA[ED8853324D7A4044880E0CB69DD6D25D]]></FIN_PAYMENT_SCHEDULE_ID>
  <AD_CLIENT_ID><![CDATA[39363B0921BB4293B48383844325E84C]]></AD_CLIENT_ID>
  <AD_ORG_ID><![CDATA[D270A5AC50874F8BA67A88EE977F8E3B]]></AD_ORG_ID>
  <CREATED><![CDATA[2014-04-22 13:10:59.116]]></CREATED>
  <CREATEDBY><![CDATA[3073EDF96A3C42CC86C7069E379522D2]]></CREATEDBY>
  <UPDATED><![CDATA[2014-04-22 13:10:59.191]]></UPDATED>
  <UPDATEDBY><![CDATA[3073EDF96A3C42CC86C7069E379522D2]]></UPDATEDBY>
  <C_INVOICE_ID><![CDATA[D69233CF4E974D20AAB145D044A7D066]]></C_INVOICE_ID>
  <DUEDATE><![CDATA[2014-04-22 13:10:57.0]]></DUEDATE>
  <FIN_PAYMENTMETHOD_ID><![CDATA[45A202BF44884F05B8A1BF741E2063B6]]></FIN_PAYMENTMETHOD_ID>
  <C_CURRENCY_ID><![CDATA[102]]></C_CURRENCY_ID>
  <AMOUNT><![CDATA[3.60]]></AMOUNT>
  <PAIDAMT><![CDATA[3.60]]></PAIDAMT>
  <OUTSTANDINGAMT><![CDATA[0]]></OUTSTANDINGAMT>
  <ISACTIVE><![CDATA[Y]]></ISACTIVE>
  <UPDATE_PAYMENT_PLAN><![CDATA[Y]]></UPDATE_PAYMENT_PLAN>
  <EXPECTEDDATE><![CDATA[2014-04-22 13:10:57.0]]></EXPECTEDDATE>
  <EM_APRM_MODIF_PAYM_SCHED><![CDATA[N]]></EM_APRM_MODIF_PAYM_SCHED>
  <EM_APRM_MODIF_PAYM_OUT_SCHED><![CDATA[N]]></EM_APRM_MODIF_PAYM_OUT_SCHED>
</FIN_PAYMENT_SCHEDULE>

<FIN_PAYMENT_SCHEDULE>
  <FIN_PAYMENT_SCHEDULE_ID><![CDATA[EF460EBA72F84FDDB587DAEEE565F8A6]]></FIN_PAYMENT_SCHEDULE_ID>
  <AD_CLIENT_ID><![CDATA[39363B0921BB4293B48383844325E84C]]></AD_CLIENT_ID>
  <AD_ORG_ID><![CDATA[3B187EC130A549A7A9388F8060EF156D]]></AD_ORG_ID>
  <CREATED><![CDATA[2013-07-04 23:01:16.702]]></CREATED>
  <CREATEDBY><![CDATA[0]]></CREATEDBY>
  <UPDATED><![CDATA[2013-07-04 23:01:16.702]]></UPDATED>
  <UPDATEDBY><![CDATA[0]]></UPDATEDBY>
  <C_INVOICE_ID><![CDATA[96D66878DFE044BCAD21BB9471C60D80]]></C_INVOICE_ID>
  <DUEDATE><![CDATA[2012-07-24 00:00:00.0]]></DUEDATE>
  <FIN_PAYMENTMETHOD_ID><![CDATA[45A202BF44884F05B8A1BF741E2063B6]]></FIN_PAYMENTMETHOD_ID>
  <C_CURRENCY_ID><![CDATA[102]]></C_CURRENCY_ID>
  <AMOUNT><![CDATA[89.8]]></AMOUNT>
  <PAIDAMT><![CDATA[89.8]]></PAIDAMT>
  <OUTSTANDINGAMT><![CDATA[0.0]]></OUTSTANDINGAMT>
  <ISACTIVE><![CDATA[Y]]></ISACTIVE>
  <UPDATE_PAYMENT_PLAN><![CDATA[Y]]></UPDATE_PAYMENT_PLAN>
  <EXPECTEDDATE><![CDATA[2012-07-24 00:00:00.0]]></EXPECTEDDATE>
  <EM_APRM_MODIF_PAYM_SCHED><![CDATA[N]]></EM_APRM_MODIF_PAYM_SCHED>
  <EM_APRM_MODIF_PAYM_OUT_SCHED><![CDATA[N]]></EM_APRM_MODIF_PAYM_OUT_SCHED>
</FIN_PAYMENT_SCHEDULE>

<FIN_PAYMENT_SCHEDULE>
  <FIN_PAYMENT_SCHEDULE_ID><![CDATA[EF71A8355C024834B43A4B330854D0C4]]></FIN_PAYMENT_SCHEDULE_ID>
  <AD_CLIENT_ID><![CDATA[39363B0921BB4293B48383844325E84C]]></AD_CLIENT_ID>
  <AD_ORG_ID><![CDATA[BF129721D9FB4EB0819509934153E972]]></AD_ORG_ID>
  <CREATED><![CDATA[2013-07-04 23:01:16.744]]></CREATED>
  <CREATEDBY><![CDATA[0]]></CREATEDBY>
  <UPDATED><![CDATA[2013-07-04 23:01:16.744]]></UPDATED>
  <UPDATEDBY><![CDATA[0]]></UPDATEDBY>
  <C_ORDER_ID><![CDATA[40F1A96A2A2C4FB891CD361C9B1479FC]]></C_ORDER_ID>
  <DUEDATE><![CDATA[2012-07-07 00:00:00.0]]></DUEDATE>
  <FIN_PAYMENTMETHOD_ID><![CDATA[5A741F883A31408CA3AC097D76AA6D32]]></FIN_PAYMENTMETHOD_ID>
  <C_CURRENCY_ID><![CDATA[102]]></C_CURRENCY_ID>
  <AMOUNT><![CDATA[1389370.40]]></AMOUNT>
  <PAIDAMT><![CDATA[0]]></PAIDAMT>
  <OUTSTANDINGAMT><![CDATA[1389370.40]]></OUTSTANDINGAMT>
  <ISACTIVE><![CDATA[Y]]></ISACTIVE>
  <UPDATE_PAYMENT_PLAN><![CDATA[Y]]></UPDATE_PAYMENT_PLAN>
  <EXPECTEDDATE><![CDATA[2012-07-07 00:00:00.0]]></EXPECTEDDATE>
  <EM_APRM_MODIF_PAYM_SCHED><![CDATA[N]]></EM_APRM_MODIF_PAYM_SCHED>
  <EM_APRM_MODIF_PAYM_OUT_SCHED><![CDATA[N]]></EM_APRM_MODIF_PAYM_OUT_SCHED>
</FIN_PAYMENT_SCHEDULE>

<FIN_PAYMENT_SCHEDULE>
  <FIN_PAYMENT_SCHEDULE_ID><![CDATA[F8DEE677E8CC4799B0D4E45DAE9B5058]]></FIN_PAYMENT_SCHEDULE_ID>
  <AD_CLIENT_ID><![CDATA[39363B0921BB4293B48383844325E84C]]></AD_CLIENT_ID>
  <AD_ORG_ID><![CDATA[D270A5AC50874F8BA67A88EE977F8E3B]]></AD_ORG_ID>
  <CREATED><![CDATA[2013-07-04 23:01:16.701]]></CREATED>
  <CREATEDBY><![CDATA[0]]></CREATEDBY>
  <UPDATED><![CDATA[2013-07-04 23:01:16.701]]></UPDATED>
  <UPDATEDBY><![CDATA[0]]></UPDATEDBY>
  <C_INVOICE_ID><![CDATA[3DFB06404EFF496089B963C9E920B9BC]]></C_INVOICE_ID>
  <DUEDATE><![CDATA[2012-07-24 15:32:05.749]]></DUEDATE>
  <FIN_PAYMENTMETHOD_ID><![CDATA[45A202BF44884F05B8A1BF741E2063B6]]></FIN_PAYMENTMETHOD_ID>
  <C_CURRENCY_ID><![CDATA[102]]></C_CURRENCY_ID>
  <AMOUNT><![CDATA[-21.0]]></AMOUNT>
  <PAIDAMT><![CDATA[-21.0]]></PAIDAMT>
  <OUTSTANDINGAMT><![CDATA[0]]></OUTSTANDINGAMT>
  <ISACTIVE><![CDATA[Y]]></ISACTIVE>
  <UPDATE_PAYMENT_PLAN><![CDATA[Y]]></UPDATE_PAYMENT_PLAN>
  <EXPECTEDDATE><![CDATA[2012-07-24 15:32:05.749]]></EXPECTEDDATE>
  <EM_APRM_MODIF_PAYM_SCHED><![CDATA[N]]></EM_APRM_MODIF_PAYM_SCHED>
  <EM_APRM_MODIF_PAYM_OUT_SCHED><![CDATA[N]]></EM_APRM_MODIF_PAYM_OUT_SCHED>
</FIN_PAYMENT_SCHEDULE>

<FIN_PAYMENT_SCHEDULE>
  <FIN_PAYMENT_SCHEDULE_ID><![CDATA[FD7622AA68D2467C869B4A205A26EE07]]></FIN_PAYMENT_SCHEDULE_ID>
  <AD_CLIENT_ID><![CDATA[39363B0921BB4293B48383844325E84C]]></AD_CLIENT_ID>
  <AD_ORG_ID><![CDATA[BF129721D9FB4EB0819509934153E972]]></AD_ORG_ID>
  <CREATED><![CDATA[2013-07-04 23:01:16.744]]></CREATED>
  <CREATEDBY><![CDATA[0]]></CREATEDBY>
  <UPDATED><![CDATA[2013-07-04 23:01:16.744]]></UPDATED>
  <UPDATEDBY><![CDATA[0]]></UPDATEDBY>
  <C_INVOICE_ID><![CDATA[00DBBFE8F5DD4681AB5C34B4DF168047]]></C_INVOICE_ID>
  <DUEDATE><![CDATA[2012-10-22 00:00:00.0]]></DUEDATE>
  <FIN_PAYMENTMETHOD_ID><![CDATA[5A741F883A31408CA3AC097D76AA6D32]]></FIN_PAYMENTMETHOD_ID>
  <C_CURRENCY_ID><![CDATA[102]]></C_CURRENCY_ID>
  <AMOUNT><![CDATA[2100.00]]></AMOUNT>
  <PAIDAMT><![CDATA[0]]></PAIDAMT>
  <OUTSTANDINGAMT><![CDATA[2100.00]]></OUTSTANDINGAMT>
  <ISACTIVE><![CDATA[Y]]></ISACTIVE>
  <UPDATE_PAYMENT_PLAN><![CDATA[Y]]></UPDATE_PAYMENT_PLAN>
  <EXPECTEDDATE><![CDATA[2012-10-22 00:00:00.0]]></EXPECTEDDATE>
  <EM_APRM_MODIF_PAYM_SCHED><![CDATA[N]]></EM_APRM_MODIF_PAYM_SCHED>
  <EM_APRM_MODIF_PAYM_OUT_SCHED><![CDATA[N]]></EM_APRM_MODIF_PAYM_OUT_SCHED>
</FIN_PAYMENT_SCHEDULE>

<FIN_PAYMENT_SCHEDULE>
  <FIN_PAYMENT_SCHEDULE_ID><![CDATA[FFF8B4694EE2467D8EE71F1B2A07D5AC]]></FIN_PAYMENT_SCHEDULE_ID>
  <AD_CLIENT_ID><![CDATA[39363B0921BB4293B48383844325E84C]]></AD_CLIENT_ID>
  <AD_ORG_ID><![CDATA[D270A5AC50874F8BA67A88EE977F8E3B]]></AD_ORG_ID>
  <CREATED><![CDATA[2013-07-04 23:01:16.703]]></CREATED>
  <CREATEDBY><![CDATA[0]]></CREATEDBY>
  <UPDATED><![CDATA[2013-07-04 23:01:16.703]]></UPDATED>
  <UPDATEDBY><![CDATA[0]]></UPDATEDBY>
  <C_ORDER_ID><![CDATA[B4AC5453766244B9B9F78F0BEE7503AB]]></C_ORDER_ID>
  <DUEDATE><![CDATA[2012-07-24 00:00:00.0]]></DUEDATE>
  <FIN_PAYMENTMETHOD_ID><![CDATA[45A202BF44884F05B8A1BF741E2063B6]]></FIN_PAYMENTMETHOD_ID>
  <C_CURRENCY_ID><![CDATA[102]]></C_CURRENCY_ID>
  <AMOUNT><![CDATA[36.5]]></AMOUNT>
  <PAIDAMT><![CDATA[36.5]]></PAIDAMT>
  <OUTSTANDINGAMT><![CDATA[0.0]]></OUTSTANDINGAMT>
  <ISACTIVE><![CDATA[Y]]></ISACTIVE>
  <UPDATE_PAYMENT_PLAN><![CDATA[Y]]></UPDATE_PAYMENT_PLAN>
  <EXPECTEDDATE><![CDATA[2012-07-24 00:00:00.0]]></EXPECTEDDATE>
  <EM_APRM_MODIF_PAYM_SCHED><![CDATA[N]]></EM_APRM_MODIF_PAYM_SCHED>
  <EM_APRM_MODIF_PAYM_OUT_SCHED><![CDATA[N]]></EM_APRM_MODIF_PAYM_OUT_SCHED>
</FIN_PAYMENT_SCHEDULE>

</data>
